Workbook

Sheet 廣交會
A1: SKU | B1: Description | C1: Location | D1: L | E1: W | F1: H | G1: FOB | H1: Unit | I1: Carton Qty | J1: Note | K1: IMG | L1: Keyword
A2: WU77683AP | B2: Lycanthrope Werewolf Moon Howl | C2: CF | D2: 5.5 | E2: 3 | F2: 8.3 | G2: 2.1 | H2: PC | I2: 1 | J2: WU | K2: https://d2smnk90fd10gg.cloudfront.net/commodity/photo/WU77683AP-1.jpg | L2: Wolves; Gothic Designs; Greek & Roman MythologyFantasy creature; Bronze; Mythological symbolism; Fantasy; Standing; Mythical; Halloween; Round base; Howling; Gothic; Werewolf; Lycanthrope; Moon Howl; Supernatural lore; Werewolf: The Apocalypse; Underworld; Greek gods, Greek goddesses, Roman gods, Roman goddesses,
A3: WU78064AP | B3: Alexander The Great | C3: CF | D3: 4.5 | E3: 4 | F3: 9.3 | G3: 2 | H3: PC | I3: 1 | J3: WU | K3: https://d2smnk90fd10gg.cloudfront.net/commodity/photo/WU78064AP-1.jpg | L3: Knights & Warriors; Greek & Roman Mythology; Warrior; MiniaturesBronze; Classical; Greek; Human form; Brown; Standing; Gold; Sword; Warrior; Historical figure; King; Rectangular base; Ruler; Armor; Helmet; Hellenistic; General; alexander the great; - Occupation if any:; Greek gods, Greek goddesses, Roman gods, Roman goddesses,
A4: WU78062AP | B4: Leonidas | C4: CF | D4: 6.5 | E4: 4 | F4: 7.7 | G4: 2.2 | H4: PC | I4: 1 | J4: WU | K4: https://d2smnk90fd10gg.cloudfront.net/commodity/photo/WU78062AP-1.JPG | L4: Knights & Warriors; Greek & Roman Mythology; Warrior; MiniaturesGreek gods, Greek goddesses, Roman gods, Roman goddesses,
A5: WU78350AA | B5: Crusader Knight Axe And Shield | C5: CF | D5: 3.5 | E5: 2.5 | F5: 8 | G5: 2.2 | H5: PC | I5: 1 | J5: WU | K5: https://d2smnk90fd10gg.cloudfront.net/commodity/photo/WU78350AA-1.jpg | L5: Knights & Warriors; MiniaturesRectangular; Classical; Black; Standing; Religious symbols; Gold; Silver; Medieval; Knight; Shield; Warrior; Christianity; Historical; Axe; Crusader; Medieval soldier; Templar
A6: WU78351AA | B6: German Ceremonial Knight Armor Sword Stance | C6: CF | D6: 3.5 | E6: 2.5 | F6: 8 | G6: 2.2 | H6: PC | I6: 1 | J6: WU | K6: https://d2smnk90fd10gg.cloudfront.net/commodity/photo/WU78351AA-1.jpg | L6: Knights & Warriors; MiniaturesClassical; Human figure; Standing; Gold; Silver; Medieval; Knight; Sword; Warrior; Steel; Armor; Chivalry; German; Sword Stance
A7: WU78353AA | B7: Medieval Knight Armor Sword Stance | C7: CF | D7: 3.5 | E7: 2.5 | F7: 8 | G7: 2.2 | H7: PC | I7: 1 | J7: WU | K7: https://d2smnk90fd10gg.cloudfront.net/commodity/photo/WU78353AA-1.jpg | L7: Knights & Warriors; MiniaturesClassical; Human form; Standing; Gold; Realistic; Silver; Medieval; Knight; Sword; Warrior; Steel; Armor; Historical; Medieval Knight; Helmeted Head; Chivalry; Armored figure; Base pedestal; Feudal; European history; Black (base); Paladin; Noble knight
A8: WU78354AA | B8: Medieval Knight Armor Sword Stance | C8: CF | D8: 3.5 | E8: 2.5 | F8: 8 | G8: 2.2 | H8: PC | I8: 1 | J8: WU | K8: https://d2smnk90fd10gg.cloudfront.net/commodity/photo/WU78354AA-1.jpg | L8: Knights & Warriors; MiniaturesHuman figure; Standing; Realistic; Medieval; Gunmetal black; Knight; Sword; Warrior; Gold accents; Soldier; Steel; Historical; Medieval Knight; European heritage; Standing base
A9: WU78117AA | B9: Sapphire Plume Peacock Wand | C9: JH | D9: 2.5 | E9: 2.5 | F9: 36 | G9: 2.4 | H9: PC | I9: 1 | J9: WU | K9: https://d2smnk90fd10gg.cloudfront.net/commodity/photo/WU78117AA-1.jpg | L9: Peacock; WiccaFantasy creature; Green; Mythological symbolism; Fantasy; Decorative; Blue; Brown; Harry Potter; Plume; Sapphire; Wand; Peacock symbolism; Wicca, wicca goddesses, wicca gods
A10: WU78118AA | B10: Owl Wand | C10: JH | D10: 2.5 | E10: 2 | F10: 36.5 | G10: 2.4 | H10: PC | I10: 1 | J10: WU | K10: https://d2smnk90fd10gg.cloudfront.net/commodity/photo/WU78118AA-1.jpg | L10: Owl; WiccaFantasy creature; Mythological symbolism; Round; Fantasy; Brown; Harry Potter; Wood; Wildlife animal; Wand; Wicca, wicca goddesses, wicca gods
A11: WU78392AP | B11: Archangel Saint Gabriel Blowing Trumpet | C11: CF | D11: 5.5 | E11: 5 | F11: 10 | G11: 2.5 | H11: PC | I11: 1 | J11: WU | K11: https://d2smnk90fd10gg.cloudfront.net/commodity/photo/WU78392AP-1.jpg | L11: Religious; AngelBronze; Classical; Standing; Metallic; Flowers; Religious symbols; Baroque; Gold; Winged; Christmas; Religious figure; Christian symbolism; Angelic symbolism; Trumpet; Archangel; Trumpet; Saint; Blowing trumpet; Divine messenger
A12: WU77707AA | B12: Vampire Count | C12: JH | D12: 6 | E12: 4 | F12: 11.5 | G12: 2.7 | H12: PC | I12: 1 | J12: WU | K12: https://d2smnk90fd10gg.cloudfront.net/commodity/photo/WU77707AA-1.jpg | L12: Gothic DesignsFantasy creature; Mythological symbolism; White; Black; Standing; Red; Gothic; Halloween; Vampire; Dracula; Nosferatu; Castlevania; Horror; Cape; Menacing
A13: WU78189AA | B13: French Bulldog Chat Room Menace | C13: CF | D13: 4.5 | E13: 6 | F13: 7.5 | G13: 2.7 | H13: PC | I13: 1 | J13: WU | K13: https://d2smnk90fd10gg.cloudfront.net/commodity/photo/WU78189AA-1.jpg | L13: Dogsfrench bulldog; Dog, Dogs, Puppy, Hound
... A23: WU77618AA | B23: Green Man Summer Berry Wall Plaque | C23: CF | D23: 14.5 | E23: 2 | F23: 9.5 | G23: 3.9 | H23: PC | I23: 1 | J23: WU | K23: https://d2smnk90fd10gg.cloudfront.net/commodity/photo/WU77618AA-1.jpg | L23: Celtic Design & Myths; Wall Plaques; Norse Myth; WiccaFantasy creature; Green; Mythological symbolism; Decorative; Classical; Nature; Brown; Nature-inspired; Leafy; Norse mythology, Norse gods, Norse goddesses, Nordic gods; Triangular; Earth tones; Nature spirit; Green Man; Pagan symbolism; Celtic design, Celtic gods, Celtic deities嚗eltic goddesses; Wicca, wicca goddesses, wicca gods
A24: WU77619AA | B24: Green Man Spring Mushroom Wall Plaque | C24: CF | D24: 14.5 | E24: 2 | F24: 10 | G24: 3.9 | H24: PC | I24: 1 | J24: WU | K24: #N/A | L24: #N/A
A25: WU78190AA | B25: Pug | C25: CF | D25: 12 | E25: 6 | F25: 9.5 | G25: 3.9 | H25: PC | I25: 1 | J25: WU | K25: https://d2smnk90fd10gg.cloudfront.net/commodity/photo/WU78190AA-1.jpg | L25: DogsDog, Dogs, Puppy, Hound
A26: WU78376AP | B26: Santa Muerte Seating On Throne Holding Scythe And Scale | C26: CF | D26: 5 | E26: 4.6 | F26: 8.4 | G26: 3.9 | H26: PC | I26: 1 | J26: WU | K26: https://d2smnk90fd10gg.cloudfront.net/commodity/photo/WU78376AP-1.jpg | L26: Skeleton, Skull, Grimreaper, Zombie; WiccaGoddess; Bronze; Brown; Religious symbols; Gold; Halloween; Scythe; Religious art; Throne; Gothic; Scale; Mexican Folk Religion; Santa Muerte; Seated; Our Lady of Holy Death; Human Skull
A27: WU78267AP | B27: Zeus Greek God Of The Sky Holding Thunderbolt With Eagle | C27: CF | D27: 7.5 | E27: 5 | F27: 11 | G27: 3.95 | H27: PC | I27: 1 | J27: WU | K27: https://d2smnk90fd10gg.cloudfront.net/commodity/photo/WU78267AP-1.jpg | L27: Greek & Roman Mythologygreek mythology; Ancient Greek; Cloud; Eagle, Falcon, Hawk; Lighting, Thunder, Thunderbolt; Zeus; Greek gods, Greek goddesses, Roman gods, Roman goddesses,
A28: WU77828A1 | B28: Triple Goddess Tealight Candle Holder | C28: JH | D28: 9 | E28: 7 | F28: 3.5 | G28: 4 | H28: PC | I28: 1 | J28: WU | K28: https://d2smnk90fd10gg.cloudfront.net/commodity/photo/WU77828A1-1.jpg | L28: Celtic Design & Myths; Candle, Incense and Oil Burner; WiccaGoddess; Bronze; Contemporary; Round; Candle holder; Wicca; Celtic; Mythological; Triple goddess; Pagan symbolism; Crescent; Pentacle; Celtic design, Celtic gods, Celtic deities嚗eltic goddesses; Wicca, wicca goddesses, wicca gods
A29: WU77846AA | B29: Triple Black Cat Candle Tea Light Holder | C29: JH | D29: 10 | E29: 10 | F29: 5 | G29: 4 | H29: PC | I29: 1 | J29: WU | K29: https://d2smnk90fd10gg.cloudfront.net/commodity/photo/WU77846AA-1.jpg | L29: Cats; Candle, Incense and Oil Burner; WiccaCat, Cats, Kitty, Kitten, Kitties; Feline figure; Kitty; Feline; Cats, Cat, Kitten, Kitty; Wicca, wicca goddesses, wicca gods
A30: WU78173AB | B30: Infant Jesus With Golden Halo | C30: JH | D30: 13.5 | E30: 4.5 | F30: 3.5 | G30: 4.3 | H30: PC | I30: 1 | J30: WU | K30: #N/A | L30: #N/A
A31: WU78232AP | B31: Hector Of Troy | C31: CF | D31: 7.5 | E31: 6 | F31: 9.5 | G31: 4.3 | H31: PC | I31: 1 | J31: WU | K31: #N/A | L31: #N/A
A32: WU78233AP | B32: Achilleus Hero Of Trojan War | C32: CF | D32: 7.8 | E32: 5 | F32: 9.5 | G32: 4.3 | H32: PC | I32: 1 | J32: WU | K32: #N/A | L32: #N/A
A33: WU78479AP | B33: Greenman Lady Of Abundance Wall Plaque | C33: CF | D33: 13.5 | E33: 14.5 | F33: 3 | G33: 4.4 | H33: PC | I33: 1 | J33: WU | K33: https://d2smnk90fd10gg.cloudfront.net/commodity/photo/WU78479AP-1.jpg | L33: Celtic Design & Myths; Home Accent; Wall Plaques; Wicca; Miniaturesartistic; Fantasy creature; Goddess; Bronze; Green; Mythological symbolism; Round; Nature; Mythical; Multicolored; Leaves; Berries; Autumn; Nature spirit
A34: WU78183A4 | B34: Yoga Elephant Headstand | C34: JH | D34: 8 | E34: 7 | F34: 9 | G34: 4.6 | H34: PC | I34: 1 | J34: WU | K34: https://d2smnk90fd10gg.cloudfront.net/commodity/photo/WU78183A4-1.jpg | L34: Yoga, Performance Art and Dance; ElephantBronze; Contemporary; Round; Purple; Yoga; Trunk; Elephant; Wildlife animal; Meditation; Inverted; Legs; Headstand
A35: WU78193A4 | B35: French Bulldog Food Delivery Carrier | C35: CF | D35: 4.5 | E35: 8 | F35: 9 | G35: 4.8 | H35: PC | I35: 1 | J35: WU | K35: https://d2smnk90fd10gg.cloudfront.net/commodity/photo/WU78193A4-1.jpg | L35: Dogsfrench bulldog; Dog, Dogs, Puppy, Hound
A36: WU77808A1 | B36: Spiral Goddess Triple Moon Tealight Candle Holder | C36: JH | D36: 7 | E36: 7 | F36: 12 | G36: 5 | H36: PC | I36: 1 | J36: WU | K36: https://d2smnk90fd10gg.cloudfront.net/commodity/photo/WU77808A1-1.jpg | L36: Celtic Design & Myths; Candle, Incense and Oil Burner; WiccaFantasy creature; Goddess; Bronze; Mythological symbolism; Contemporary; Round; Abstract; Standing; Spiral; Religious symbols; Tealight holder; Celtic design, Celtic gods, Celtic deities嚗eltic goddesses; Wicca, wicca goddesses, wicca gods
A37: WU78251AP | B37: See Hear Speak No Evil Skull Pen Holder | C37: JH | D37: 11.5 | E37: 11.5 | F37: 10 | G37: 5 | H37: PC | I37: 1 | J37: WU | K37: https://d2smnk90fd10gg.cloudfront.net/commodity/photo/WU78251AP-1.jpg | L37: Gothic Designs; Skeleton, Skull, Grimreaper, Zombie; Vase and Vessel; Studies DecorSkull; Human skull; Skeleton; See No Evil; Hear No Evil; Three Wise Monkeys
A38: WU78277AA | B38: Our Lady Of Fatima | C38: CF | D38: 5.5 | E38: 4.5 | F38: 15.5 | G38: 5 | H38: PC | I38: 1 | J38: WU | K38: https://d2smnk90fd10gg.cloudfront.net/commodity/photo/WU78277AA-1.jpg | L38: Mary, Mother of JesusWhite; Gold; Crown; Mary; Blessed Virgin Mary; Mother Mary
A39: WU78280AA | B39: The Immaculate Heart Of Mary | C39: CF | D39: 5 | E39: 5 | F39: 15.5 | G39: 5 | H39: PC | I39: 1 | J39: WU | K39: https://d2smnk90fd10gg.cloudfront.net/commodity/photo/WU78280AA-1.jpg | L39: Mary, Mother of JesusWhite; Blue; Religious; Mary; Blessed Virgin Mary; Mother Mary
A40: WU78186AA | B40: The Wardens Of The Damned Pen Holder | C40: JH | D40: 12 | E40: 10.5 | F40: 12.5 | G40: 5.2 | H40: PC | I40: 1 | J40: WU | K40: https://d2smnk90fd10gg.cloudfront.net/commodity/photo/WU78186AA-1.jpg | L40: Skeleton, Skull, Grimreaper, Zombie; Vase and Vessel; Studies DecorFantasy creature; Mythological symbolism; Fantasy; Rectangular; Standing; Gothic; Halloween; Game of Thrones; Gunmetal black; Grim Reaper; Staff; Skeleton; Stone grey; Tower; Medieval; Dark Souls; Diablo; Warden; Fortress; Hooded cloak
A41: WU77634A4 | B41: Hear No Evil Viking | C41: JH | D41: 8.8 | E41: 8 | F41: 10 | G41: 5.3 | H41: PC | I41: 1 | J41: WU | K41: https://d2smnk90fd10gg.cloudfront.net/commodity/photo/WU77634A4-1.jpg | L41: Knights & Warriors; Norse MythNorse mythology, Norse gods, Norse goddesses, Nordic gods; Humanoid figures; See No Evil; Hear No Evil; Speak No Evil; Three Wise Monkeys; Trio; Covering ears, eyes, mouth; Vikings; Viking
A42: WU77635A4 | B42: See No Evil Viking | C42: CF | D42: 8.5 | E42: 7.5 | F42: 10 | G42: 5.3 | H42: PC | I42: 1 | J42: WU | K42: https://d2smnk90fd10gg.cloudfront.net/commodity/photo/WU77635A4-1.jpg | L42: Knights & Warriors; Norse MythNorse mythology, Norse gods, Norse goddesses, Nordic gods; See No Evil; Hear No Evil; Speak No Evil; Three Wise Monkeys; Trio; Covering ears, eyes, mouth; Vikings; Viking
A43: WU77636A4 | B43: Speak No Evil Viking | C43: CF | D43: 9 | E43: 7 | F43: 10 | G43: 5.3 | H43: PC | I43: 1 | J43: WU | K43: https://d2smnk90fd10gg.cloudfront.net/commodity/photo/WU77636A4-1.jpg | L43: Knights & Warriors; Norse MythNorse mythology, Norse gods, Norse goddesses, Nordic gods; Scandinavian; Vikings (TV Series); Humanoid figures; See No Evil; Hear No Evil; Speak No Evil; Three Wise Monkeys; Trio; Covering ears, eyes, mouth; Vikings; Viking
A44: WU78274AA | B44: Jesus Christ Divine Mercy | C44: CF | D44: 5.5 | E44: 6.5 | F44: 16 | G44: 5.4 | H44: PC | I44: 1 | J44: WU | K44: https://d2smnk90fd10gg.cloudfront.net/commodity/photo/WU78274AA-1.jpg | L44: Gospel of Jesus, Christ, Son of GodBlue; Red; Jesus; Off-white
... A55: WU78363AA | B55: Cardinal Bird Couple Perching On Snowy Branch | C55: CF | D55: 9 | E55: 7 | F55: 15.5 | G55: 6.6 | H55: PC | I55: 1 | J55: WU | K55: https://d2smnk90fd10gg.cloudfront.net/commodity/photo/WU78363AA-1.jpg | L55: Animal; BirdGreen; White; Brown; Nature-inspired; Realistic; Red; Christmas; Branch; Perching; Berries; Round base; Winter; Snow; Wildlife animal; Branch; Cardinal birds; Northern Cardinals
A56: WU78132AA1 | B56: Hail Mary Prayer Photo Frame | C56: CF | D56: 12 | E56: 3 | F56: 19 | G56: 6.8 | H56: PC | I56: 1 | J56: WU | K56: #N/A | L56: #N/A
A57: WU77621A4 | B57: Battling Crusader Hinged Trinket Chest | C57: JH | D57: 11.8 | E57: 7.5 | F57: 5.8 | G57: 7 | H57: PC | I57: 1 | J57: WU | K57: https://d2smnk90fd10gg.cloudfront.net/commodity/photo/WU77621A4-1.jpg | L57: Knights & Warriors; Trinket BoxBronze; Rectangular; Religious symbols; Silver; Gunmetal black; Knight; Sword; Shield; Riding; Warrior; Historical figure; Historical; Crusader; Medieval
A58: WU78272AA | B58: Saint Francis Of Assisi | C58: CF | D58: 9 | E58: 6.5 | F58: 15.5 | G58: 7 | H58: PC | I58: 1 | J58: WU | K58: https://d2smnk90fd10gg.cloudfront.net/commodity/photo/WU78272AA-1.jpg | L58: SaintsBrown; Dove; Cross; Monk; Catholic iconography; Deer
A59: WU78400AA | B59: Crouching Gargoyle | C59: JH | D59: 11.5 | E59: 12 | F59: 14.5 | G59: 7 | H59: PC | I59: 1 | J59: WU | K59: https://d2smnk90fd10gg.cloudfront.net/commodity/photo/WU78400AA-1.jpg | L59: Myth & Legend; Gothic DesignsFantasy creature; Crouching; Pedestal; Grey; ; - Alternative Names if any:; Wings; Protector; Guardian; Gothic; Halloween; Stone; Gargoyle; Charcoal; Medieval; ; - Shape or Elements:; Rectangular Base; Gothic; Winged; Crouching; Gargoyles (TV series); Demon statue; Stone guardian; Crouching; Architectural; Snarling
A60: WU78402AA | B60: Imp Face Gargoyle Crouching On Pedestal | C60: JH | D60: 11 | E60: 11 | F60: 17.5 | G60: 7 | H60: PC | I60: 1 | J60: WU | K60: https://d2smnk90fd10gg.cloudfront.net/commodity/photo/WU78402AA-1.jpg | L60: Myth & Legend; Gothic DesignsFantasy creature; Crouching; Pedestal; Wings; Guardian; Gothic; Halloween; Medieval; Gunmetal black; Stone grey; Gargoyle; Gothic; Pedestal; Crouching; Demon statue; Stone guardian; European mythology
A61: WU78418AA | B61: Beast Gargoyle Thinker Pose On Pedestal | C61: JH | D61: 14 | E61: 9 | F61: 18 | G61: 7 | H61: PC | I61: 1 | J61: WU | K61: https://d2smnk90fd10gg.cloudfront.net/commodity/photo/WU78418AA-1.jpg | L61: Myth & Legend; Gothic DesignsFantasy creature; Mythological symbolism; Pedestal; Winged; Gothic; Halloween; Medieval; Gunmetal black; Gargoyle; Gothic; Pedestal; Stone gray; Seated; Beast; Demon; Thinker pose
A62: WU78422AA | B62: Maltese Knights Hospitaller Spear And Shield | C62: JH | D62: 11 | E62: 8 | F62: 19.5 | G62: 7 | H62: PC | I62: 1 | J62: WU | K62: https://d2smnk90fd10gg.cloudfront.net/commodity/photo/WU78422AA-1.jpg | L62: Knights & WarriorsWhite; Standing; Realistic; Religious symbolism; Red; Silver; Knight; Shield; Warrior; Historical; Spear; Medieval; Soldier; Round shield; Long spear; Crusader; Hospitaller
A63: WU77431AA | B63: Cosplay Kids - Abracadabra | C63: JH | D63: 8.5 | E63: 8 | F63: 16 | G63: 7.2 | H63: PC | I63: 1 | J63: WU | K63: https://d2smnk90fd10gg.cloudfront.net/commodity/photo/WU77431AA-1.jpg | L63: Gothic Designs; Cosplay Kids; WiccaFantasy creature; Fantasy; White; Black; Standing; Red; Harry Potter; Witch; Day of the Dead; Gothic; Cat; Crystal ball; Halloween; Circular (base); Sorceress; Witch hat; Fortune teller; Wicca, wicca goddesses, wicca gods
A64: WU78152AA | B64: Cosplay Kids Skeleton Fairy Metamorphosis | C64: CF | D64: 10 | E64: 10 | F64: 12 | G64: 7.2 | H64: PC | I64: 1 | J64: WU | K64: https://d2smnk90fd10gg.cloudfront.net/commodity/photo/WU78152AA-1.jpg | L64: Skeleton, Skull, Grimreaper, Zombie; Cosplay KidsFantasy creature; Green; Contemporary; Fantasy; White; Pink; Black; Wings; Purple; Halloween; Day of the Dead; Gothic; Flowers; Sugar Skull; Cat; Skeleton fairy
A65: WU78205A4 | B65: Asclepius Greek God Of Medicine | C65: CF | D65: 6 | E65: 6.5 | F65: 16 | G65: 7.2 | H65: PC | I65: 1 | J65: WU | K65: https://d2smnk90fd10gg.cloudfront.net/commodity/photo/WU78205A4-1.jpg | L65: Greek & Roman MythologyBronze; Green; Mythological symbolism; Classical; Greek; Brown; Standing; Religious symbols; Historical figure; God; Round base; Staff; Snake; Physician; Healer; Aesculapius; Healing; Greek gods, Greek goddesses, Roman gods, Roman goddesses,
A66: WU77601AA | B66: Cosplay Kids Medusa | C66: JH | D66: 8 | E66: 7 | F66: 14.5 | G66: 7.3 | H66: PC | I66: 1 | J66: WU | K66: https://d2smnk90fd10gg.cloudfront.net/commodity/photo/WU77601AA-1.jpg | L66: Greek & Roman Mythology; Cosplay KidsFantasy creature; Goddess; Green; Mythological symbolism; Contemporary; Round; Fantasy; White; Kneeling; Blue; Greek; Mythological figure; Gold; Red; Serpentine; Staff; Percy Jackson; Clash of the Titans; Medusa; Greek gods, Greek goddesses, Roman gods, Roman goddesses,
A67: WU78372AA | B67: Knights Templar Crusader Wielding Sword And Shield | C67: JH | D67: 11 | E67: 8.5 | F67: 20 | G67: 7.5 | H67: PC | I67: 1 | J67: WU | K67: https://d2smnk90fd10gg.cloudfront.net/commodity/photo/WU78372AA-1.jpg | L67: Knights & WarriorsWhite; Black; Standing; Religious symbols; Realistic; Red; Silver; Knight; Sword; Shield; Warrior; Christianity; Historical; Helmet; Round (shield); Crusader; Templar Knight; Kingdom of Heaven; Crusades; Assassin's Creed; Warrior; Medieval; Knight; Wielding
A68: WU78373AA | B68: Knights Hospitaller Wielding Sword And Shield | C68: JH | D68: 11 | E68: 8 | F68: 18 | G68: 7.5 | H68: PC | I68: 1 | J68: WU | K68: https://d2smnk90fd10gg.cloudfront.net/commodity/photo/WU78373AA-1.jpg | L68: Knights & WarriorsWhite; Black; Standing; Silver; Medieval; Sword; Shield; Warrior; Christian symbolism; Historical; Kingdom of Heaven; Crusades; Assassin's Creed; Warrior; Knight; Sword; Armor; Helmet; Medieval knight; Shield; Wielding; Defending; Knights Hospitaller; Knights of Malta; Order of St. John; Malta Cross
... A74: WU78208A4 | B74: Ares The Greek God Of War | C74: CF | D74: 7.5 | E74: 6 | F74: 16 | G74: 8 | H74: PC | I74: 1 | J74: WU | K74: https://d2smnk90fd10gg.cloudfront.net/commodity/photo/WU78208A4-1.jpg | L74: Greek & Roman MythologyMythological symbolism; Classical; Greek; Standing; Sword; Shield; Warrior; Historical figure; God; Round (shield); Rectangular (base); Greek mythology; ; - Colors or Color Mapping:; Bronze; Gold; War; God of War; Red; Mars; Greek gods, Greek goddesses, Roman gods, Roman goddesses,
A75: WU78244AA | B75: Saint Pio Of Pietrelcina (Padre Pio) | C75: CF | D75: 7.5 | E75: 6 | F75: 21.5 | G75: 8 | H75: PC | I75: 1 | J75: WU | K75: #N/A | L75: #N/A
A76: WU77574A4 | B76: Divine Infant Jesus (El Divino Nino) | C76: JH | D76: 9 | E76: 6 | F76: 17.5 | G76: 8.5 | H76: PC | I76: 1 | J76: WU | K76: https://d2smnk90fd10gg.cloudfront.net/commodity/photo/WU77574A4-1.jpg | L76: Gospel of Jesus, Christ, Son of God
A77: WU78200A4 | B77: Steampunk Jet Engine Skater Mouse | C77: JH | D77: 12 | E77: 7 | F77: 14.5 | G77: 8.6 | H77: PC | I77: 1 | J77: WU | K77: https://d2smnk90fd10gg.cloudfront.net/commodity/photo/WU78200A4-1.jpg | L77: Steampunk; Other AnimalsFantasy creature; Bronze; Green; Round; Fantasy; Brown; Gunmetal black; Retro; Bioshock; Balancing; Circular base; Goggles; Skating; Steampunk; Adventurer; Aviator; Mouse; Gear-like; Skateboard; Jet engine; Ratatouille (thematically mouse-related)
A78: WU78201A4 | B78: Steampunk Mice Riding On Scooter | C78: JH | D78: 6 | E78: 9 | F78: 14 | G78: 8.6 | H78: PC | I78: 1 | J78: WU | K78: https://d2smnk90fd10gg.cloudfront.net/commodity/photo/WU78201A4-1.jpg | L78: Steampunk; Other AnimalsFantasy creature; Bronze; Round; Gunmetal; Riding; Steampunk; Retro; Animal; Pink accents; Copper; Teal; Scooter; Cylindrical elements
A79: WU78194Y4 | B79: Infant Jesus Golden Halo And The Holy Manger | C79: CF | D79: 14.5 | E79: 8 | F79: 10 | G79: 9.2 | H79: PC | I79: 1 | J79: WU | K79: https://d2smnk90fd10gg.cloudfront.net/commodity/photo/WU78194Y4-1.jpg | L79: Gospel of Jesus, Christ, Son of God; Nativity of JesusBronze; Classical; Reclining; Oval; Religious symbols; Baroque; Gold; Red; Christmas; Religious figure; Christian symbolism; Biblical; Infant Jesus; Manger; Halo
A80: WU78480A4 | B80: Coronation Of The Blessed Virgin Wall Plaque | C80: JH | D80: 15.5 | E80: 1.5 | F80: 23.2 | G80: 9.3 | H80: PC | I80: 1 | J80: WU | K80: #N/A | L80: #N/A
A81: WU78375A4 | B81: Medieval Knights Templar Icon Chalice Cup | C81: JH | D81: 8.5 | E81: 8.5 | F81: 17.5 | G81: 9.5 | H81: PC | I81: 1 | J81: WU | K81: https://d2smnk90fd10gg.cloudfront.net/commodity/photo/WU78375A4-1.jpg | L81: Knights & Warriors; Cup and GlasswareBronze; Red accents; Round; Standing; Religious symbols; Silver; Medieval; Sword; Shield; Warrior; Historical figure; Knight Templar; Assassin's Creed; Medieval; Knight; Gothic; Chalice; Chalice; Knights Templar; Crusader; Monty Python and the Holy Grail; Knights
A82: WU78401AA2 | B82: The Innocence Of Blessed Virgin Mary Standing Framed Plaque | C82: JH | D82: 15.5 | E82: 1.5 | F82: 23.2 | G82: 9.5 | H82: PC | I82: 1 | J82: GOV | K82: #N/A | L82: #N/A
A83: WU78099A4 | B83: Pan The Greek God Of The Wild | C83: JH | D83: 10 | E83: 6 | F83: 15.5 | G83: 9.9 | H83: PC | I83: 1 | J83: WU | K83: https://d2smnk90fd10gg.cloudfront.net/commodity/photo/WU78099A4-1.JPG | L83: Celtic Design & Myths; Greek & Roman MythologyCeltic design, Celtic gods, Celtic deities嚗eltic goddesses; Greek gods, Greek goddesses, Roman gods, Roman goddesses,
A84: WU78107A4 | B84: Spartan King Leonidas With Spear And Shield | C84: JH | D84: 11.7 | E84: 7 | F84: 15.5 | G84: 9.9 | H84: PC | I84: 1 | J84: WU | K84: https://d2smnk90fd10gg.cloudfront.net/commodity/photo/WU78107A4-1.JPG | L84: Knights & Warriors; Greek & Roman Mythology; WarriorGreek gods, Greek goddesses, Roman gods, Roman goddesses,
A85: WU78342AA | B85: Silky Smooth Barber Shop Exothermic Poodle Perm | C85: CF | D85: 6.5 | E85: 9 | F85: 13.5 | G85: 9.9 | H85: PC | I85: 1 | J85: WU | K85: https://d2smnk90fd10gg.cloudfront.net/commodity/photo/WU78342AA-1.jpg | L85: Animal; DogsGreen; Contemporary; Round; Pink; Whimsical; Black; Orange; Silver; Reading; Book; Chair; Barber; Domestic animal; Dog; Book; Seated; Poodle; Hairrollers; Salon Chair; Hairstylist
A86: WU78478A4 | B86: Greek Sphinx The Riddler Of Thebes | C86: CF | D86: 14 | E86: 13.5 | F86: 17 | G86: 10.2 | H86: PC | I86: 1 | J86: WU | K86: https://d2smnk90fd10gg.cloudfront.net/commodity/photo/WU78478A4-1.jpg | L86: Egyptian; Myth & Legend; Greek & Roman Mythology; WiccaFantasy creature; Bronze; Mythological symbolism; Classical; Greek; Brown; Mythological figure; Gold; Winged; Feline form; Seated; Prowling stance; Oedipus Rex; Theban Riddler
A87: WU78084A4 | B87: Mother Of Dragons | C87: CF | D87: 8 | E87: 9.5 | F87: 18 | G87: 10.3 | H87: PC | I87: 1 | J87: WU | K87: https://d2smnk90fd10gg.cloudfront.net/commodity/photo/WU78084A4-1.jpg | L87: Female Nudes; DragonFantasy creature; Goddess; Bronze; Red accents; Mythological symbolism; Fantasy; Kneeling; Human form; Game of Thrones; Dragon
A88: WU77584A4 | B88: Sitting Shiva | C88: CF | D88: 12.5 | E88: 7 | F88: 15.7 | G88: 10.5 | H88: PC | I88: 1 | J88: WU | K88: https://d2smnk90fd10gg.cloudfront.net/commodity/photo/WU77584A4-1.jpg | L88: HinduismHinduism, Hindu, Hindi, Indian, Hindu gods, Hindu god
A89: WU77600A4 | B89: Saint Benedict Crucifix Wall Plaque With Stand | C89: CF | D89: 11 | E89: 7.5 | F89: 24.5 | G89: 10.5 | H89: PC | I89: 1 | J89: WU | K89: https://d2smnk90fd10gg.cloudfront.net/commodity/photo/WU77600A4-1.jpg | L89: Cross, Crucifixes and Calvary; SaintsBronze; Rectangular; Classical; Ornate; Religious symbols; Gold; Traditional; Silver; Cross; Jesus Christ; Crucifix; Christianity; Crucified; Religious art; Catholicism; Saint Benedict; INRI
A90: WU78265A1 | B90: Breathtaking Astronaut Bring Your Child To Space Day | C90: CF | D90: 13 | E90: 11.5 | F90: 19 | G90: 10.5 | H90: PC | I90: 1 | J90: WU | K90: https://d2smnk90fd10gg.cloudfront.net/commodity/photo/WU78265A1-1.jpg | L90: Galaxies; ProfessionalsBronze; Family; Astronaut, cosmonaut, spaceman; Interstellar
A91: WU77629A4 | B91: Ludwig Van Beethoven Music Box | C91: CF | D91: 10.7 | E91: 10 | F91: 14.3 | G91: 10.8 | H91: PC | I91: 1 | J91: WU | K91: https://d2smnk90fd10gg.cloudfront.net/commodity/photo/WU77629A4-1.jpg | L91: Musician & Composer; Music BoxBronze; Rectangular; Classical; Baroque; Historical figure; Wood; Composer; Classical music; Sheet music; Ornate base
A92: WU76356A4 | B92: Hanuman - Hindu God Of Strength | C92: JH | D92: 10 | E92: 9.5 | F92: 27.5 | G92: 12.5 | H92: PC | I92: 1 | J92: TOPLIND | K92: #N/A | L92: #N/A
A93: WU77791A4 | B93: The Forest Nymph Elemental | C93: JH | D93: 9.5 | E93: 14 | F93: 25 | G93: 11.5 | H93: PC | I93: 1 | J93: WU | K93: https://d2smnk90fd10gg.cloudfront.net/commodity/photo/WU77791A4-1.jpg | L93: Fairy; Celtic Design & Myths; Greek & Roman Mythology; WiccaFantasy creature; Bronze; Green; Mythological symbolism; Contemporary; Abstract; Standing; Nature symbolism; Nymph; Flowing; Reaching; Tree-like; Celtic design, Celtic gods, Celtic deities嚗eltic goddesses; Greek gods, Greek goddesses, Roman gods, Roman goddesses,; Wicca, wicca goddesses, wicca gods
A94: WU77801A4 | B94: The Forest Nymph Shimmer | C94: JH | D94: 12 | E94: 10 | F94: 26 | G94: 11.5 | H94: PC | I94: 1 | J94: WU | K94: https://d2smnk90fd10gg.cloudfront.net/commodity/photo/WU77801A4-1.jpg | L94: Fairy; Celtic Design & Myths; Greek & Roman Mythology; WiccaFantasy creature; Bronze; Green; Mythological symbolism; Contemporary; Curved; Brown; Standing; Nature symbolism; Nymph; Organic; Reaching; Earth tones; The Lord of the Rings; Narnia; Mythological; Fantasy art; Tree-like; Tree spirit; Celtic design, Celtic gods, Celtic deities嚗eltic goddesses; Greek gods, Greek goddesses, Roman gods, Roman goddesses,; Wicca, wicca goddesses, wicca gods
A95: WU77698A4 | B95: Head Of Medusa Wall Plaque (H:18Cm) | C95: CF | D95: 13 | E95: 5.5 | F95: 18.5 | G95: 12 | H95: PC | I95: 1 | J95: WU | K95: https://d2smnk90fd10gg.cloudfront.net/commodity/photo/WU77698A4-1.jpg | L95: Greek & Roman Mythology; Wall PlaquesBronze; Mythological symbolism; Classical; Metallic; Oval; Mythological creature; Clash of the Titans; Mythological; Greek mythology; Gorgon; Medusa; Snakes; Percy Jackson series; Greek gods, Greek goddesses, Roman gods, Roman goddesses,
A96: WU78287A4 | B96: Little Girl Kneeling Prayer Into Your Hands I Commit My Spirit | C96: JH | D96: 12 | E96: 13.5 | F96: 14.5 | G96: 12 | H96: PC | I96: 1 | J96: WU | K96: https://d2smnk90fd10gg.cloudfront.net/commodity/photo/WU78287A4-1.jpg | L96: Faith and InspirationalBronze; Red accents; Girl; Young girl; Religious; Prayer pose; Prayer hands
A97: WU78300A4 | B97: Tattooed Male In Tights Stretching Pinup Pose | C97: JH | D97: 12.5 | E97: 9 | F97: 30 | G97: 12 | H97: PC | I97: 1 | J97: WU | K97: https://d2smnk90fd10gg.cloudfront.net/commodity/photo/WU78300A4-1.jpg | L97: Male NudesMuscular; Male Nude; Beach; LGBTQ, gay, lesbian, trans, gender
A98: WU78407A4 | B98: Calliope The Greek Muse Of Epics | C98: CF | D98: 8 | E98: 9 | F98: 23 | G98: 12 | H98: PC | I98: 1 | J98: WU | K98: https://d2smnk90fd10gg.cloudfront.net/commodity/photo/WU78407A4-1.jpg | L98: Greek & Roman Mythologygreek mythology; Greek; Female figure; Instrument; Robed figure; Circular base; Draped robe; Ancient Greek
A99: WU78236A4 | B99: Narcissus And His Reflection | C99: JH | D99: 17 | E99: 12 | F99: 10.5 | G99: 12.1 | H99: PC | I99: 1 | J99: WU | K99: https://d2smnk90fd10gg.cloudfront.net/commodity/photo/WU78236A4-1.jpg | L99: Greek & Roman MythologyBronze; Green; Mythological symbolism; White; Classical; Kneeling; Blue; Greek; Human form; Mythological figure; Flowers; Narcissus; Realism; Gazing; Water reflection; Greek gods, Greek goddesses, Roman gods, Roman goddesses,
A100: WU77826A4 | B100: Steampunk Exoskeleton Warrior Woman | C100: JH | D100: 11.5 | E100: 13 | F100: 24 | G100: 12.2 | H100: PC | I100: 1 | K100: https://d2smnk90fd10gg.cloudfront.net/commodity/photo/WU77826A4-1.jpg | L100: Knights & Warriors; SteampunkBronze; Fantasy; Standing; Gold; Gothic; Gunmetal black; Sword; Steampunk; Retro; Round base; Detailed armor; Warrior; Medieval; Knight; Hand on hip; Fantasy knight; Armor
A101: WU76539A4 | B101: Seated Lakshmi - Hindu Goddess Of Wealth, Prosperity, And Wisdom | C101: JH | D101: 12.5 | E101: 9.5 | F101: 18 | G101: 13.5 | H101: PC | I101: 1 | J101: WU | K101: #N/A | L101: #N/A
A102: WU78070A4 | B102: Lady Of The Lake And Excalibur | C102: JH | D102: 11.5 | E102: 11 | F102: 33.5 | G102: 12.8 | H102: PC | I102: 1 | J102: WU | K102: https://d2smnk90fd10gg.cloudfront.net/commodity/photo/WU78070A4-1.jpg | L102: Celtic Design & MythsBronze; Mythological symbolism; Classical; Mythological figure; Fantasy figure; Gold; Sword; Flowing gown; Arthurian legend; King Arthur; Standing; Mythological; Celtic design, Celtic gods, Celtic deities嚗eltic goddesses; Lady of the Lake; Excalibur; Holding sword aloft
A103: WU76590A4 | B103: Wall Plaque-St.Benedict Crucifix | C103: JH | D103: 35.5 | E103: 20.5 | F103: 4.5 | G103: 13 | H103: PC | I103: 1 | J103: GOV | K103: #N/A | L103: #N/A
A104: WU77680A4 | B104: Cyclops Wielding Spiked Mace | C104: JH | D104: 15 | E104: 13.5 | F104: 21.2 | G104: 13 | H104: PC | I104: 1 | J104: WU | K104: https://d2smnk90fd10gg.cloudfront.net/commodity/photo/WU77680A4-1.jpg | L104: Greek & Roman MythologyFantasy creature; Bronze; Mythological symbolism; Round; Classical; Greek; Standing; Metallic; Mythological figure; Realistic; Gunmetal black; Warrior; Muscular; Clash of the Titans; Mythological; God of War; Wielding; Spiked mace; Cyclops; Mace; Skull emblem; Threatening pose; Odyssey; Greek gods, Greek goddesses, Roman gods, Roman goddesses,
A105: WU77944A4 | B105: Ishtar The Babylonian Goddess Of War And Fertility | C105: CF | D105: 12 | E105: 6 | F105: 21.5 | G105: 13 | H105: PC | I105: 1 | J105: WU | K105: https://d2smnk90fd10gg.cloudfront.net/commodity/photo/WU77944A4-1.jpg | L105: Wicca; Mesopotamian legendsGoddess; Bronze; Mythological symbolism; Round; Classical; Standing; Metallic; Religious symbols; Gold; Winged; Historical figure; Star; Animal figures; Mythological; Owl; Lion; Wand; Babylon; Ancient Mesopotamia; Star symbol; Greek gods, Greek goddesses, Roman gods, Roman goddesses,; Wicca, wicca goddesses, wicca gods
A106: WU78059A4 | B106: Steampunk Gauntlet Of Love | C106: CF | D106: 13 | E106: 9.5 | F106: 24 | G106: 13 | H106: PC | I106: 1 | J106: WU | K106: https://d2smnk90fd10gg.cloudfront.net/commodity/photo/WU78059A4-1.jpg | L106: SteampunkBronze; Red accents; Gunmetal black; Retro; Bioshock; Hand; Futuristic; Cyberpunk; Steampunk; Gear; Fantasy item
A107: WU78074A4 | B107: Steampunk Gauntlet Of Goodwill | C107: CF | D107: 13.5 | E107: 10 | F107: 25.5 | G107: 13 | H107: PC | I107: 1 | J107: WU | K107: https://d2smnk90fd10gg.cloudfront.net/commodity/photo/WU78074A4-1.jpg | L107: SteampunkFantasy creature; Bronze; Gunmetal black; Steampunk; Bioshock; Victorian; Brass; Hand; Futuristic; Copper; Industrial Revolution; Gears; Gear; Pipes; Steampunk symbolism; Steampunk novels; Valves; Mechanical Hand; Mechanical Gauntlet; Steam-powered Glove; Gauntlet; Open palm
A108: WU77599AA | B108: Hocus Pocus By Lisa Parker | C108: CF | D108: 16.8 | E108: 10.3 | F108: 13.3 | G108: 13.1 | H108: PC | I108: 1 | J108: NEM | K108: https://d2smnk90fd10gg.cloudfront.net/commodity/photo/WU77599AA-1.jpg | L108: Cats; WiccaCat, Cats, Kitty, Kitten, Kitties; Harry Potter; Feline figure; Kitty; Feline; Cats, Cat, Kitten, Kitty; Mystical; Wizard; Sorcerer; Magician; Magic; Wicca, wicca goddesses, wicca gods
A109: WU77566A4 | B109: Virgin Mary | C109: CF | D109: 9.5 | E109: 8 | F109: 28.2 | G109: 13.2 | H109: PC | I109: 1 | J109: WU | K109: #N/A | L109: #N/A
A110: WU78073AA | B110: Grand Snowy Owl Of Wisdom | C110: JH | D110: 14.5 | E110: 12 | F110: 24.5 | G110: 13.2 | H110: PC | I110: 1 | J110: WU | K110: https://d2smnk90fd10gg.cloudfront.net/commodity/photo/WU78073AA-1.jpg | L110: Owl; WiccaFantasy creature; Mythological symbolism; White; Classical; Brown; Cream; Perched; Harry Potter; Scroll; Arch; Wildlife animal; Gothic; Book; Ink bottle; Wicca, wicca goddesses, wicca gods
A111: WU77497A4 | B111: Murmillo Gladiator Spartacus Wielding Scutum And Gladius | C111: JH | D111: 13.5 | E111: 11.3 | F111: 26 | G111: 13.5 | H111: PC | I111: 1 | J111: WU | K111: https://d2smnk90fd10gg.cloudfront.net/commodity/photo/WU77497A4-1.jpg | L111: Leaders; Knights & Warriors; Greek & Roman Mythology; WarriorBronze; Rectangular; Classical; Standing; Gunmetal black; Sword; Shield; Warrior; Historical figure; Historical; Rome; Round elements; Armor; Gladiator; Spartacus; Roman symbolism; Greek gods, Greek goddesses, Roman gods, Roman goddesses,
A112: WU77726A4 | B112: Greek Hero Hector Of Troy Holding Sword And Shield | C112: JH | D112: 15.5 | E112: 8.5 | F112: 23.5 | G112: 13.5 | H112: PC | I112: 1 | J112: IB.GR | K112: https://d2smnk90fd10gg.cloudfront.net/commodity/photo/WU77726A4-1.jpg | L112: Knights & Warriors; Greek & Roman MythologyBronze; Mythological symbolism; Classical; Greek; Standing; Gunmetal black; Sword; Shield; Historical figure; Round (shield); Warrior; Iliad; Greek gods, Greek goddesses, Roman gods, Roman goddesses,
A113: WU78199A4 | B113: Cerberus The Three Headed Hound Of Hades | C113: JH | D113: 13 | E113: 19.5 | F113: 13.5 | G113: 13.6 | H113: PC | I113: 1 | J113: WU | K113: https://d2smnk90fd10gg.cloudfront.net/commodity/photo/WU78199A4-1.jpg | L113: Dogs; Greek & Roman Mythologygreek mythology; Greek; Dog, Dogs, Puppy, Hound; Ancient Greek; Greek gods, Greek goddesses, Roman gods, Roman goddesses,
A114: WU77552A4 | B114: “Lady Of Grace” With Polyptych Sculpture Of Pieta | C114: JH | D114: 7 | E114: 6 | F114: 20.5 | G114: 13.8 | H114: PC | I114: 1 | J114: WU | K114: https://d2smnk90fd10gg.cloudfront.net/commodity/photo/WU77552A4-1.jpg | L114: Mary, Mother of Jesus; Nativity of JesusBronze; Rectangular; Classical; Holding; Brown; Religious symbols; Gold; Embracing; Silver; Christian Iconography; Historical figure; Jesus Christ; Virgin Mary; Religious art; Patina; Gothic; Religious symbol; Pieta; Crown; Gothic architecture; Tri-panel
A115: WU77608A4 | B115: Bastet Eygptian Goddess Of Protection | C115: JH | D115: 15.5 | E115: 9.2 | F115: 25.5 | G115: 13.8 | H115: PC | I115: 1 | J115: WU | K115: https://d2smnk90fd10gg.cloudfront.net/commodity/photo/WU77608A4-1.jpg | L115: EgyptianGoddess; Bronze; Mythological symbolism; Black; Human form; Standing; Religious symbols; Gold; Protector; Traditional; Egyptian; Ankh; Egyptian deity; Ancient art; Cat; Bast; Cat features
A116: WU77727A4 | B116: Greek Hero Achilles Holding Sword And Shield | C116: JH | D116: 15.5 | E116: 11.5 | F116: 24 | G116: 13.8 | H116: PC | I116: 1 | J116: IB.GR | K116: https://d2smnk90fd10gg.cloudfront.net/commodity/photo/WU77727A4-1.JPG | L116: Knights & Warriors; Greek & Roman MythologyBronze; Mythological symbolism; Classical; Greek; Standing; Metallic; Sword; Shield; Historical figure; Ancient Greek; Warrior; Round shield; Greek hero; Troy; Muscular form; Combat stance; The Iliad; Greek gods, Greek goddesses, Roman gods, Roman goddesses,
A117: WU78213A4 | B117: Cernunnos The Celtic God Of The Wild | C117: JH | D117: 12.5 | E117: 8 | F117: 27 | G117: 13.8 | H117: PC | I117: 1 | J117: ＷＵ | K117: https://d2smnk90fd10gg.cloudfront.net/commodity/photo/WU78213A4-1.jpg | L117: Celtic Design & Myths; WiccaBronze; Green; Mythological symbolism; Classical; Standing; Mythological figure; Gold; God; Pagan; Antlers; Celtic; Mythological; Staff; Celtic deity; Horned God; Celtic design, Celtic gods, Celtic deities嚗eltic goddesses; Wicca, wicca goddesses, wicca gods
A118: WU77906AA | B118: Siesta Fairy | C118: JH | D118: 15 | E118: 7.5 | F118: 16.5 | G118: 14 | H118: PC | I118: 1 | J118: WU | K118: #N/A | L118: #N/A
A119: WU77914A1 | B119: Sigil Of Baphomet Occult Altar Backflow Incense Burner | C119: CF | D119: 14.5 | E119: 9.5 | F119: 18.5 | G119: 14 | H119: PC | I119: 1 | J119: WU | K119: https://d2smnk90fd10gg.cloudfront.net/commodity/photo/WU77914A1-1.jpg | L119: Gothic Designs; Wicca; Baphomet DesignsFantasy creature; Bronze; Pedestal; Standing; Metallic; Circular; Religious symbols; Halloween; Dark Art; Star; Cauldron; Gothic; Goat deity; Occult symbolism; Occult figure; Occult altar; Incense burner; Wicca, wicca goddesses, wicca gods
A120: WU77936AA | B120: Armor Clad Litch King | C120: JH | D120: 14 | E120: 12.5 | F120: 25.5 | G120: 14 | H120: PC | I120: 1 | J120: WU | K120: https://d2smnk90fd10gg.cloudfront.net/commodity/photo/WU77936AA-1.jpg | L120: Skeleton, Skull, Grimreaper, Zombie; Knights & WarriorsFantasy creature; Mythological symbolism; Fantasy; Standing; Silver; Halloween; Gunmetal black; Warrior; Gold accents; Armor; Medieval; Dark Souls; Sword; Gothic; Helmet; King; Lich King; World of Warcraft
A121: WU78014A4 | B121: Celtic Earth Mother Goddess Danu | C121: JH | D121: 13 | E121: 16 | F121: 23 | G121: 14 | H121: PC | I121: 1 | J121: WU | K121: https://d2smnk90fd10gg.cloudfront.net/commodity/photo/WU78014A4-1.jpg | L121: Celtic Design & Myths; WiccaFantasy creature; Goddess; Bronze; Green; Mythological symbolism; Classical; Blue; Standing; Organic forms; Religious symbols; Gold; Flowing Water; Historical figure; Earth tones; Pouring; Celtic; Mythological; Danu; Celtic design, Celtic gods, Celtic deities嚗eltic goddesses; Earth Mother; Waterfall; Wicca, wicca goddesses, wicca gods
A122: WU78264AA | B122: Inferno Skeleton Sovereign | C122: CF | D122: 15 | E122: 15.5 | F122: 22 | G122: 14 | H122: PC | I122: 1 | J122: WU | K122: https://d2smnk90fd10gg.cloudfront.net/commodity/photo/WU78264AA-1.jpg | L122: Gothic Designs; Skeleton, Skull, Grimreaper, ZombieSkull; Staff; Skeleton; Armored Warrior; Flames; Fantasy character; Dark fantasy; Torch
A123: WU78301A4 | B123: Tattooed Male Sitting On Rock Beach Pinup | C123: JH | D123: 12.5 | E123: 18 | F123: 21.5 | G123: 14 | H123: PC | I123: 1 | J123: WU | K123: https://d2smnk90fd10gg.cloudfront.net/commodity/photo/WU78301A4-1.jpg | L123: Male NudesRock; Male Nude; Rock base; Beach; LGBTQ, gay, lesbian, trans, gender
A124: WU78302A4 | B124: Tattooed Male In Jeans Pin Up Crossed Legs Lean On Rock | C124: JH | D124: 21 | E124: 9 | F124: 20 | G124: 14 | H124: PC | I124: 1 | J124: WU | K124: https://d2smnk90fd10gg.cloudfront.net/commodity/photo/WU78302A4-1.jpg | L124: Male NudesRock; Nude; Male Torso; Male figure; Male Nude; Rock base; Beach
...

Sheet Sheet6
A1: sku | B1: tags_names | C1: photos
A2: WU78629AP | B2: Bronze; Mythological symbolism; Classical; Greek; Standing; Gold; Warrior; Realism; Bow; Figurative; Bow; Arrow; King; Ulysses; The Odyssey; Odysseus; Drawing bow; Dog (Argos); Ithacan King; Heroic | C2: https://d2smnk90fd10gg.cloudfront.net/commodity/photo/WU78629AP-1.jpg
A3: WU78618A4 | B3: Fantasy creature; Bronze; Mythological symbolism; Curved; Standing; Metallic; Organic; Fox; Wildlife animal; Celtic; Mythological; ; - Poses or Actions:; Celtic art; Drawing bow; Seated | C3: https://d2smnk90fd10gg.cloudfront.net/commodity/photo/WU78618A4-1.jpg
A4: WU78615A4 | B4: Bronze; Mythological symbolism; Contemporary; Blue; Nautical; Flowing Water; Jumping; Wildlife animal; Celtic; Waves; Celtic art; Humpback Whale; Knotwork | C4: https://d2smnk90fd10gg.cloudfront.net/commodity/photo/WU78615A4-1.jpg
A5: WU78609A4 | B5: Fantasy creature; Bronze; Green; Mythological symbolism; Round; Modern; Nautical; Halloween; Gunmetal black; Gothic; Tentacles; Lovecraftian; Mythological being; Cthulhu; Great Old One; Tankard; H.P. Lovecraft works | C5: https://d2smnk90fd10gg.cloudfront.net/commodity/photo/WU78609A4-1.jpg
A6: WU78604AP | B6: Fantasy creature; Bronze; Green; Mythological symbolism; Rectangular; Mythical; Nautical; Halloween; Gunmetal black; Lovecraftian; Cthulhu; Cthulhu Mythos | C6: https://d2smnk90fd10gg.cloudfront.net/commodity/photo/WU78604AP-1.jpg
A7: WU78605A4 | B7: Goddess; Bronze; Mythological symbolism; Classical; Greek; Standing; Metallic; Winged; Warrior; Earth tones; Percy Jackson; Horses; Trumpet; Chariot; Chariot; Winged Victory; Holding trumpet | C7: https://d2smnk90fd10gg.cloudfront.net/commodity/photo/WU78605A4-1.jpg
A8: WU78626A4 | B8: Bronze; Green; Classical; Brown; Standing; Red; Shield; Warrior; Historical figure; Mother; Circular base; Armor; Historical; Rome; Leader; Spear; Celtic; Historical symbolism; Boadicea; Boudicca; Marching | C8: https://d2smnk90fd10gg.cloudfront.net/commodity/photo/WU78626A4-1.jpg
A9: WU78624A4 | B9: Fantasy creature; Bronze; Mythological symbolism; Classical; Greek; Metallic; Warrior; Bow; Dynamic; Earth tones; Rearing; Mythological art; Archer; Centaur; Arrow; Bow and arrow; Drawing bow | C9: https://d2smnk90fd10gg.cloudfront.net/commodity/photo/WU78624A4-1.jpg
A10: WU78616A4 | B10: Bronze; Round; Classical; Floral; Religious symbols; Baroque; Gold; Lid; Angel; Rose; Wings; Cherub; Silver; Angelic symbolism; Urn; Seated; Guardian Angel Urn; Winged cherub | C10: https://d2smnk90fd10gg.cloudfront.net/commodity/photo/WU78616A4-1.jpg
A11: WU78614A4 | B11: Bronze; Classical; Metallic; Religious symbols; Renaissance; Religious figure; Cross; Jesus; Christian symbolism; Round base; Mary; La Pietà; Patina; Seated | C11: https://d2smnk90fd10gg.cloudfront.net/commodity/photo/WU78614A4-1.jpg
A12: WU78606A4 | B12: Bronze; Mythological symbolism; Classical; Greek; Standing; Mythological figure; Gold; Nautical; Waves; God; Percy Jackson; Trident; Poseidon; Neptune; God of War; Water deity | C12: https://d2smnk90fd10gg.cloudfront.net/commodity/photo/WU78606A4-1.jpg
... A47: WU78523A4 | B47: Bronze; Mythological symbolism; Round; Classical; Greek; Standing; Sword; Shield; Warrior; Historical figure; Marble; Ancient; Ancient Greece; Clash of the Titans; Mythological art; Sword; Mythological hero; Greek hero; Hero; Classical hues; Head of Medusa (element); Medusa's head; Triumphant pose | C47: https://d2smnk90fd10gg.cloudfront.net/commodity/photo/WU78523A4-1.jpg
A48: WU78503AA | C48: https://d2smnk90fd10gg.cloudfront.net/commodity/photo/WU78503AA-1.jpg
A49: WU73129BA | B49: Goddess; Bronze; Classical; Standing; Gold; Embracing; Sword; Shield; God; Love; Marble; Classical symbolism; Mythological figures; Renaissance; Mythological; Roman mythology; War | C49: https://d2smnk90fd10gg.cloudfront.net/commodity/photo/WU73129BA-1.jpg
A50: WU70783BA | B50: Mythological symbolism; Classical; Greek; Religious symbols; Gold; ; - Alternative Names if any:; God; Marble; Scepter; Percy Jackson; Clash of the Titans; Zeus; Throne; Seated | C50: https://d2smnk90fd10gg.cloudfront.net/commodity/photo/WU70783BA-1.jpg
A51: WU78610A4 | B51: Fantasy creature; Mythological symbolism; Contemporary; White; Standing; Maiden; - Alternative Names if any:; Gothic; Halloween; Gunmetal black; Marble; Skeleton; - Cultural or Symbolic Elements:; Memento Mori | C51: https://d2smnk90fd10gg.cloudfront.net/commodity/photo/WU78610A4-1.JPG
A52: WU78599A4 | B52: mythological; Goddess; Sea deity; Ocean symbolism; Inuit deity; Inuit mythology | C52: https://d2smnk90fd10gg.cloudfront.net/commodity/photo/WU78599A4-1.JPG
A53: WU78595A4 | B53: Bronze; Mythological symbolism; Curved; Nautical; Traditional; Dragon; Warrior; Wood; Long; Gliding; Historical; Drakkar; Norse; Scandinavian; Sail; Shields; Vikings (TV Series); Assassin's Creed Valhalla; How to Train Your Dragon; Off-white; Longship; Sailing; Navigator; Viking; Dragon Head; Explorer; Boat; Metallic silver; The Last Kingdom; Seafarer; Viking Age; Oar; Clan; Nordic Blue; Narrow; Hull; Craftsmanship; Mast; Navigating; Northmen; Shipbuilder; Snekke; Longship Display; Viking Tray; Nordic Vessel | C53: https://d2smnk90fd10gg.cloudfront.net/commodity/photo/WU78595A4-1.jpg
A54: WU78587VA | B54: Bronze; Contemporary; White; Rectangular; Resting; Realistic; Lying down; Wood; Wildlife animal; Dog; Cocker Spaniel; Curved edges; Spaniel Urn; Cocker Urn; Pet Memorial Urn; Pet Memorial; Grief Symbol | C54: https://d2smnk90fd10gg.cloudfront.net/commodity/photo/WU78587VA-1.JPG
A55: WU78583AA | B55: Rectangular; Religious symbols; Gold; Christmas; Gothic; Medieval; Christianity; Marble; Stone; Saints; The Da Vinci Code; Cathedral; Tower-like; Church Miniature; Religious Display; Cathedrals | C55: https://d2smnk90fd10gg.cloudfront.net/commodity/photo/WU78583AA-1.JPG
A56: WU78582BA | B56: Green; Contemporary; White; Decorative; Pastel; Pink; Floral; Spring; Petal; Nature-inspired; Bloom; Charm; Blossom | C56: https://d2smnk90fd10gg.cloudfront.net/commodity/photo/WU78582BA-1.JPG
A57: WU78582A4 | B57: Pastel; Floral; Curved; Petal; - Alternative Names if any:; Soft tones; Floral form; Charm; Petal color; Charm color; Delicate shape | C57: https://d2smnk90fd10gg.cloudfront.net/commodity/photo/WU78582A4-1.JPG
A58: WU78578BA | B58: Goddess; Mythological symbolism; White; Classical; Pastel; Floral; Greek; Modern; Human figure; Curved; Petal; Standing; Flowing; Romanticism; Graceful; - Alternative Names if any:; Victorian; Marble; - Movie, book, anime, manga, game titles that shares the same th; Floral form; - Shape or Elements:; - Style or Artistic Influence:; - Poses or Actions:; Charm; Mythical being; - Seasonal attribute if any:; Delicate shape; Rose gold; Victorian elegance | C58: https://d2smnk90fd10gg.cloudfront.net/commodity/photo/WU78578BA-1.JPG
A59: WU78578A4 | B59: Fantasy creature; Goddess; Bronze; Contemporary; White; Classical; Standing; Elegant; Graceful; - Alternative Names if any:; Marble; - Objects if any:; - Poses or Actions:; - Seasonal attribute if any: | C59: https://d2smnk90fd10gg.cloudfront.net/commodity/photo/WU78578A4-1.JPG
A60: WU75343BA | B60: Goddess; Mythological symbolism; White; Classical; Greek; Standing; Ivory; Historical figure; Youth; Marble; Greek mythology; Hebe; divine youth | C60: https://d2smnk90fd10gg.cloudfront.net/commodity/photo/WU75343BA-1.JPG
... A110: WU78536AA | B110: Fantasy creature; Green; Mythological symbolism; Face; Fantasy; Brown; Nature-inspired; Oval; Halloween; Wall-mounted; Wood; Mystical; The Witcher; Lord of the Rings; Earthy tones; Tree spirit; Forest guardian; Tree Man; Woodland spirit; Nature warden; Nature connection; Druidic symbolism | C110: https://d2smnk90fd10gg.cloudfront.net/commodity/photo/WU78536AA-1.jpg
A111: WU78535AA | C111: https://d2smnk90fd10gg.cloudfront.net/commodity/photo/WU78535AA-1.jpg
A112: WU78528AA | B112: Bronze; Nautical; Shield; Warrior; Wood; Historical; Viking ship; Drakkar; Norse; Vikings (TV Series); Assassin's Creed Valhalla; Longship; Viking; Boat; Sailor; Viking Longship; Norse ship; Oar | C112: https://d2smnk90fd10gg.cloudfront.net/commodity/photo/WU78528AA-1.jpg
A113: WU78521AA | B113: Contemporary; Curved; Organic; Minimalist; Fluid; Soft White; Serene Blue; Gentle Pink | C113: https://d2smnk90fd10gg.cloudfront.net/commodity/photo/WU78521AA-1.jpg
A114: WU78512AA | B114: Fantasy creature; Mythological symbolism; White; Classical; Standing; Religious symbols; Baroque; Gold; Winged; Angel; - Alternative Names if any:; Flying; Halo; - Colors or Color Mapping:; - Shape or Elements:; - Style or Artistic Influence:; - Objects if any:; - Poses or Actions:; - Seasonal attribute if any:; Soft White; Serene Blue; Gentle Pink; Celestial Companions; Divine Allies | C114: https://d2smnk90fd10gg.cloudfront.net/commodity/photo/WU78512AA-1.JPG
A115: WU78508A4 | B115: mythological; Fantasy creature; Mythological symbolism; Round; Trinket box; Circular; Traditional; Wood; Stone; Norse; Vikings; Viking; Mythical animal; God of War; Runes; Wolf Trinket Box; Norse Wolf Box | C115: https://d2smnk90fd10gg.cloudfront.net/commodity/photo/WU78508A4-1.jpg
A116: WU78346YA | B116: Contemporary; White; Lying; Realism; Running; Horses; Strength; Freedom; Wildlife animal; Prancing; Wild nature | C116: https://d2smnk90fd10gg.cloudfront.net/commodity/photo/WU78346YA-1.jpg
A117: WU78538A4 | B117: mythological; Goddess; Bronze; Green; Mythological symbolism; Classical; Standing; Mythological figure; - Alternative Names if any:; Triangular; Tree; Earth tones; Triple Goddess; Pagan symbolism; Feminine archetypes | C117: https://d2smnk90fd10gg.cloudfront.net/commodity/photo/WU78538A4-1.jpg
A118: WU78532A4 | B118: Bronze; Contemporary; Kneeling; Brown; Realistic; - Alternative Names if any:; Girl; Hugging; Blue accents; Puppy; Dog | C118: https://d2smnk90fd10gg.cloudfront.net/commodity/photo/WU78532A4-1.jpg
A119: WU78520A4 | B119: Bronze; Mythological symbolism; Classical; Greek; Mythological figure; Wings; Flying; Cloud; Ascending; Icarus | C119: https://d2smnk90fd10gg.cloudfront.net/commodity/photo/WU78520A4-1.jpg
A120: WU78518A4 | B120: mythological; Bronze; Green; Mythological symbolism; Classical; Blue; Human form; Standing; Gold; Flowing Water; Fish; water; God; Gesturing; Sumerian deity; Sumerian culture; Ea | C120: https://d2smnk90fd10gg.cloudfront.net/commodity/photo/WU78518A4-1.jpg
A121: WU78511AP | B121: mythological; Bronze; Green; Mythological symbolism; Round; Gold; Winged; Silver; Medieval; Shield; Warrior; Norse; Falcon; Axe; Viking; Twin Axe; Crossed; Spread Wings | C121: https://d2smnk90fd10gg.cloudfront.net/commodity/photo/WU78511AP-1.jpg
A122: WU78505A4 | B122: Bronze; Human figure; Standing; Multicolored; Religious symbols; Gold; Traditional; Crown; Owl; Religious; Roses; Death symbolism; Santa Muerte; Mexican; Saint of Death | C122: https://d2smnk90fd10gg.cloudfront.net/commodity/photo/WU78505A4-1.jpg
A123: WU78504AP | B123: Bronze; Mythological symbolism; Classical; Brown; Standing; Gold; Religious symbolism; Red; God; Round base; Torch; Celtic; Celtic deity; Holding torch | C123: https://d2smnk90fd10gg.cloudfront.net/commodity/photo/WU78504AP-2.jpg
... A193: WU78382AA | B193: Fantasy creature; Mythological symbolism; Contemporary; Fairy; Fantasy; Pastel; Pink; Kneeling; Blue; Ladybug; Nature symbolism; Multicolored; Winged; Mushroom; Iridescent; Mushroom; Paintbrush | C193: https://d2smnk90fd10gg.cloudfront.net/commodity/photo/WU78382AA-1.jpg
A194: WU78379AA | C194: https://d2smnk90fd10gg.cloudfront.net/commodity/photo/WU78379AA-1.jpg
A195: WU78374AA | B195: Green; Contemporary; Round; White; Floral; Spring; Blue; Oval; Flowers; Orange; Realistic; Bird; Perching; Flower pot; Wildlife animal; Bluebird | C195: https://d2smnk90fd10gg.cloudfront.net/commodity/photo/WU78374AA-1.jpg
A196: WU78371AA | B196: Fantasy creature; Green; Mythological symbolism; Fantasy; White; Classical; Pink; Resting; Winged; Lotus; Swan; Baby; Seated | C196: https://d2smnk90fd10gg.cloudfront.net/commodity/photo/WU78371AA-1.jpg
A197: WU78370AA | B197: Fantasy creature; Green; Mythological symbolism; Contemporary; Fairy; Flower; Fantasy; Pink; Spring; Kneeling; Leaf; Nature symbolism; Mythical; Yellow; Wings; Oval base; Wildlife animal; Pastel colors; Snail; Cerulean Blue; Interaction with nature | C197: https://d2smnk90fd10gg.cloudfront.net/commodity/photo/WU78370AA-1.jpg
A198: WU78360AA | B198: Fantasy creature; Green; Mythological symbolism; Contemporary; Fantasy; Brown; Yellow; Wings; Multicolor; Branch; Wildlife animal; Flowers; Seated; Cyan; Tropical | C198: https://d2smnk90fd10gg.cloudfront.net/commodity/photo/WU78360AA-1.jpg
A199: WU78359AA | B199: Green; Contemporary; White; Pink; Whimsical; Standing; Beige; Stool; Circular base; Hairdryer; Scissors; Poodle; Shih Tzu; Dog Groomer; Black and White Checkered; Grooming; Hairdresser; Groomer | C199: https://d2smnk90fd10gg.cloudfront.net/commodity/photo/WU78359AA-1.jpg
A200: WU78442A4 | B200: Fantasy creature; Bronze; Contemporary; Round; Brown; Gold; Purple; Gunmetal black; Riding; Retro; Futuristic; Sunglasses; Cyberpunk; Motorcycle; Cat; Biker; Motorcycle; Biker; Seated; Headband | C200: https://d2smnk90fd10gg.cloudfront.net/commodity/photo/WU78442A4-1.jpg
A201: WU78420A4 | B201: Bronze; Green; Mythological symbolism; Classical; Standing; Mythological figure; Gold; Sword; God; Human Figure; Harp; Instrument; Celtic; Celtic; Swan; Irish | C201: https://d2smnk90fd10gg.cloudfront.net/commodity/photo/WU78420A4-1.jpg
A202: WU78423A4 | B202: Classical; Black; Silver; Medieval; Sword; Shield; Warrior; Historical figure; Steel; Round (shield); Knight; ; - Cultural or Symbolic Elements:; Religious symbols; Medieval; Knights Hospitaller; Knights of Malta; Order of St. John; Red (often associated with knightly coats of arms); Crusader; Christian; Cross (popular symbol among knights); The Crusades (general theme) | C202: https://d2smnk90fd10gg.cloudfront.net/commodity/photo/WU78423A4-1.jpg
A203: WU78392YP | B203: Bronze; Classical; Standing; Religious symbols; Gold; Winged; Guardian; Religious figure; Sword; Shield; Christian symbolism; Religious art; Messenger; Staff; Trumpet; Scroll; Archangel; Sculptural figures | C203: https://d2smnk90fd10gg.cloudfront.net/commodity/photo/WU78392YP-1.jpg
A204: WU78423AA | B204: White; Rectangular; Black; Standing; Silver; Medieval; Sword; Shield; Warrior; Historical; Maltese Cross; Assassin's Creed; Knight; Shield; Medieval Warrior; Knights Hospitaller; Knight of Malta; Crusaders | C204: https://d2smnk90fd10gg.cloudfront.net/commodity/photo/WU78423AA-1.jpg
A205: WU78422AA | B205: White; Standing; Realistic; Religious symbolism; Red; Silver; Knight; Shield; Warrior; Historical; Spear; Medieval; Soldier; Round shield; Long spear; Crusader; Hospitaller | C205: https://d2smnk90fd10gg.cloudfront.net/commodity/photo/WU78422AA-1.jpg
A206: WU78454A4 | B206: Bronze; Standing; Realistic; Rifle; Western; ; Dog; Western; Americana; Cowboy | C206: https://d2smnk90fd10gg.cloudfront.net/commodity/photo/WU78454A4-1.jpg
... A221: WU78428V1 | B221: Bronze; Classical; Greek; Human figure; Standing; Roman; Male Torso; Muscular; Anatomical | C221: https://d2smnk90fd10gg.cloudfront.net/commodity/photo/WU78428V1-1.jpg
A222: WU78424AP | C222: https://d2smnk90fd10gg.cloudfront.net/commodity/photo/WU78424AP-1.jpg
A223: WU78401A4 | B223: Bronze; Rectangular; Classical; Holding; Standing; Religious symbols; Cradling; Christmas; Relief; Religious figure; Historical figure; Easter; Christian symbolism; Child; Religious; Religious art; Mary; Blessed Virgin Mary; Gold tones; Lamb; Lamb; Green patina; Blessed Virgin Mary; Mother and child; Lamb symbolism; Renaissance influence | C223: https://d2smnk90fd10gg.cloudfront.net/commodity/photo/WU78401A4-1.jpg
A224: WU78398AP | B224: Bronze; Classical; Standing; Religious symbols; Gold; Winged; Guide; Religious figure; Christianity; Robed figure; Staff; Fish; Archangel; Healer; Green highlights | C224: https://d2smnk90fd10gg.cloudfront.net/commodity/photo/WU78398AP-1.jpg
A225: WU78397AP | B225: Bronze; Classical; Standing; Religious symbols; Baroque; Wings; Religious figure; Sword; Shield; Warrior; Christian symbolism; Holding Sword; Gold tones; Archangel; Saint Michael; Shield | C225: https://d2smnk90fd10gg.cloudfront.net/commodity/photo/WU78397AP-1.jpg
A226: WU78396AP | B226: Bronze; Classical; Standing; Metallic; Gold; Angel; Religious symbolism; Wings; Religious figure; Traditional; Cross; Christian Iconography; Sword; Warrior; Cross; Archangel | C226: https://d2smnk90fd10gg.cloudfront.net/commodity/photo/WU78396AP-1.jpg
A227: WU78395AP | B227: Bronze; Red accents; Mythological symbolism; Classical; Standing; Religious symbols; Cup; Gold; Winged; Angel; Religious figure; Staff; Archangel; Detailed; Angel of Love; Chamuel; Angelic; Heart symbol | C227: https://d2smnk90fd10gg.cloudfront.net/commodity/photo/WU78395AP-1.jpg
A228: WU78394AP | B228: Bronze; Classical; Standing; Mythological figure; Religious symbols; Winged; Scroll; Angelic symbolism; Torch; Torch; Scroll; Archangel; Holding a torch | C228: https://d2smnk90fd10gg.cloudfront.net/commodity/photo/WU78394AP-1.jpg
A229: WU78393AP | B229: Bronze; Mythological symbolism; Classical; Holding; Human form; Standing; Religious symbols; Gold; Winged; Guardian; Religious figure; Sword; Religious art; Earth tones; Book; Archangel; Angel of Beauty | C229: https://d2smnk90fd10gg.cloudfront.net/commodity/photo/WU78393AP-1.jpg
A230: WU78392AP | B230: Bronze; Classical; Standing; Metallic; Flowers; Religious symbols; Baroque; Gold; Winged; Christmas; Religious figure; Christian symbolism; Angelic symbolism; Trumpet; Archangel; Trumpet; Saint; Blowing trumpet; Divine messenger | C230: https://d2smnk90fd10gg.cloudfront.net/commodity/photo/WU78392AP-1.jpg
A231: WU78326AA | B231: Bronze; White; Religious symbols; Baroque; Gold; Red; Halloween; Grim Reaper; Scythe; Religious art; Deity; Throne; Skeleton; Justice symbolism; Death symbolism; Globe; Skulls; Mexican culture; Scale; Scale; Holy Death; Santa Muerte; Dia de los Muertos; Seated; La Santísima Muerte | C231: https://d2smnk90fd10gg.cloudfront.net/commodity/photo/WU78326AA-1.jpg
A232: WU78237YC* | B232: Chess, chess man set, chessman, chess set
A233: WU78237YB*
A234: WU78146AA | B234: Mythological symbolism; Classical; Black; Human form; Standing; Mythological figure; Religious symbols; Gold; Guardian; Sword; Warrior; God; Egyptian; The Mummy; Stargate; Egyptian Revival; Mythological; Wielding; Khopesh; Animal attributes; Anubis | C234: https://d2smnk90fd10gg.cloudfront.net/commodity/photo/WU78146AA-1.jpg
A235: WU78129AA | B235: Mythological symbolism; Classical; Black; Standing; Mythological figure; Religious symbols; Gold; God; Egyptian; Ankh; Mythological; Ankh; Anubis; Scale; Scale; humanoid | C235: https://d2smnk90fd10gg.cloudfront.net/commodity/photo/WU78129AA-1.jpg
A236: WU75641YA
A237: MU09380AA
A238: S.SAMPLE
A239: CU02419AP1
A240: WU78403A4 | B240: Female figure; Mermaid; Nautical; The Little Mermaid; Nautical theme; Sea Shell; Nautical creature; Nude Female; Trident; Greek gods, Greek goddesses, Roman gods, Roman goddesses, | C240: https://d2smnk90fd10gg.cloudfront.net/commodity/photo/WU78403A4-1.jpg
A241: WU77763AB
A242: WU78419AA | B242: Fantasy creature; Mythological symbolism; Pedestal; Winged; Guardian; Gothic; Halloween; Medieval; Gunmetal black; Gray; Stone; Gargoyle; Medieval; Gothic; Pedestal; Seated; Leg crossed | C242: https://d2smnk90fd10gg.cloudfront.net/commodity/photo/WU78419AA-1.jpg
A243: WU78418AA | B243: Fantasy creature; Mythological symbolism; Pedestal; Winged; Gothic; Halloween; Medieval; Gunmetal black; Gargoyle; Gothic; Pedestal; Stone gray; Seated; Beast; Demon; Thinker pose | C243: https://d2smnk90fd10gg.cloudfront.net/commodity/photo/WU78418AA-1.jpg
A244: WU78414AP | B244: Green; Blue; Human form; Standing; Religious symbols; Baroque; Gold; Red; Christmas; Religious figure; Historical figure; Religious art; Marian apparition; Mexican culture; Catholicism; Halo; Hands Clasped; Virgen de Guadalupe; Our Lady of Tepeyac; Virgin Mary symbolism; Starry mantle; Spanish colonial art; Advent; Prayerful posture | C244: https://d2smnk90fd10gg.cloudfront.net/commodity/photo/WU78414AP-1.jpg
A245: WU78411AA | B245: Fantasy creature; Mythological symbolism; Classical; Kneeling; Winged; Guardian; Gothic; Halloween; Gunmetal black; Gray; Muscular; Stone; Gargoyle; Gothic; Menacing; Architectural ornament; Gargoyles (TV series) | C245: https://d2smnk90fd10gg.cloudfront.net/commodity/photo/WU78411AA-1.jpg
A246: WU78410A4 | B246: Nature symbolism; God; Celtic God, Celtic symbolism; Drum; Dog, Dogs, Puppy, Hound; Celtic design, Celtic gods, Celtic deities，Celtic goddesses | C246: https://d2smnk90fd10gg.cloudfront.net/commodity/photo/WU78410A4-1.jpg
A247: WU78408A4 | B247: greek mythology; Greek; Female figure; Maiden; Instrument; Robed figure; Ancient Greece; Greek gods, Greek goddesses, Roman gods, Roman goddesses, | C247: https://d2smnk90fd10gg.cloudfront.net/commodity/photo/WU78408A4-1.jpg
A248: WU78407A4 | B248: greek mythology; Greek; Female figure; Instrument; Robed figure; Circular base; Draped robe; Ancient Greek | C248: https://d2smnk90fd10gg.cloudfront.net/commodity/photo/WU78407A4-1.jpg
A249: WU78406A4 | B249: Greek; Female figure; Instrument; Flute; Roman; Classical influence; Ancient Greek; Greek gods, Greek goddesses, Roman gods, Roman goddesses, | C249: https://d2smnk90fd10gg.cloudfront.net/commodity/photo/WU78406A4-1.jpg
A250: WU78405A4 | B250: Bronze; Mythological symbolism; Round; Classical; Blue; Greek; Percy Jackson; Mythological; God of War; Clock Hands; Greek gods; Olympian deities; Radiant design; Standing figures | C250: https://d2smnk90fd10gg.cloudfront.net/commodity/photo/WU78405A4-1.jpg
A251: WU78402AA | B251: Fantasy creature; Crouching; Pedestal; Wings; Guardian; Gothic; Halloween; Medieval; Gunmetal black; Stone grey; Gargoyle; Gothic; Pedestal; Crouching; Demon statue; Stone guardian; European mythology | C251: https://d2smnk90fd10gg.cloudfront.net/commodity/photo/WU78402AA-1.jpg
A252: WU78400AA | B252: Fantasy creature; Crouching; Pedestal; Grey; ; - Alternative Names if any:; Wings; Protector; Guardian; Gothic; Halloween; Stone; Gargoyle; Charcoal; Medieval; ; - Shape or Elements:; Rectangular Base; Gothic; Winged; Crouching; Gargoyles (TV series); Demon statue; Stone guardian; Crouching; Architectural; Snarling | C252: https://d2smnk90fd10gg.cloudfront.net/commodity/photo/WU78400AA-1.jpg
A253: WU78399A4 | B253: Bronze; Classical; Ornate; Religious symbols; Baroque; Gold; Angels; Christmas; Silver; Cross; Easter; Jesus; Christian symbolism; The Passion of the Christ; The Bible; Ascending | C253: https://d2smnk90fd10gg.cloudfront.net/commodity/photo/WU78399A4-1.jpg
... A321: WU71543AD | B321: Angel; Christian Iconography; Christian legend; Demon; Christian warrior; Armored Warrior; Christian Imagery | C321: https://d2smnk90fd10gg.cloudfront.net/commodity/photo/WU71543AD-1.jpg
A322: WU74821AA
A323: AT04692A2
A324: WU77745AB*
A325: WU77692YP*
A326: HPL027-PBZ-BD
A327: HPL027-PBZ
A328: WU77499AA | B328: Rectangular; Angel; Jesus; Matt white; Patina; Rosary, Prayer | C328: https://d2smnk90fd10gg.cloudfront.net/commodity/photo/WU77499AA-1.jpg
A329: WU77500AA | B329: Rectangular; Jesus; Matt white; Cloud; Rosary, Prayer | C329: https://d2smnk90fd10gg.cloudfront.net/commodity/photo/WU77500AA-1.jpg
A330: WU77501AA | B330: Rectangular; Angel; Mary; Matt white; Patina; Rosary, Prayer | C330: https://d2smnk90fd10gg.cloudfront.net/commodity/photo/WU77501AA-1.jpg
A331: WU77502AA | B331: Rectangular; Nativity; Infant Jesus; Baby Jesus; Mary; Joseph; Matt white; Patina; Rosary, Prayer | C331: https://d2smnk90fd10gg.cloudfront.net/commodity/photo/WU77502AA-1.jpg
A332: WU77503AA | B332: Rectangular; Jesus; Matt white; Patina; Rosary, Prayer | C332: https://d2smnk90fd10gg.cloudfront.net/commodity/photo/WU77503AA-1.jpg
A333: WU77504AA | B333: Rectangular; Cross; Jesus; Matt white; Patina; Rosary, Prayer | C333: https://d2smnk90fd10gg.cloudfront.net/commodity/photo/WU77504AA-1.jpg
...

Sheet Sheet5
A1: SKU | B1: TITLE | C1: L | D1: W | E1: H | F1: FOB | J1: Location
A2: AT09084A2 | B2: Hades God Of The Greek Underworld | C2: 5.5 | D2: 4.5 | E2: 11 | F2: 8.5 | G2: PC | H2: 24 | J2: =VLOOKUP(A2,'廣交會'!A:C,3,false) -> CF
A3: AT09085A4 | B3: Medusa The Gorgon Drawing The Bow | C3: 6.5 | D3: 4.5 | E3: 11.5 | F3: 8.3 | G3: PC | H3: 24 | I3: WU(IB.GR) | J3: =VLOOKUP(A3,'廣交會'!A:C,3,false) -> CF
A4: AT09086A2 | B4: Zeus Greek God Of The Sky | C4: 7.5 | D4: 5 | E4: 11 | F4: 8.5 | G4: PC | H4: 24 | J4: =VLOOKUP(A4,'廣交會'!A:C,3,false) -> CF
A5: AT09087A4 | B5: Athena Greek Goddess Of Wisdom And Warfare | C5: 9.5 | D5: 6 | E5: 10.5 | F5: 8.3 | G5: PC | H5: 24 | J5: =VLOOKUP(A5,'廣交會'!A:C,3,false) -> CF
A6: AT09088A4 | B6: Winged Nike Of Samothrace | C6: 5 | D6: 6.5 | E6: 10.5 | F6: 8.3 | G6: PC | H6: 24 | J6: =VLOOKUP(A6,'廣交會'!A:C,3,false) -> CF
A7: AT09089A4 | B7: Oceanus The Primordial Titan Of Water | C7: 7 | D7: 5.5 | E7: 10 | F7: 8.5 | G7: PC | H7: 24 | J7: =VLOOKUP(A7,'廣交會'!A:C,3,false) -> CF
A8: AT09093A2 | B8: Hippocrates Of Cos Holding Hippocratic Oath | C8: 5 | D8: 3 | E8: 11 | F8: 8.5 | G8: PC | H8: 48 | J8: =VLOOKUP(A8,'廣交會'!A:C,3,false) -> CF
A9: AT09094A2 | B9: La Justica | C9: 4 | D9: 4.5 | E9: 11 | F9: 8.5 | G9: PC | H9: 48 | J9: =VLOOKUP(A9,'廣交會'!A:C,3,false) -> CF
A10: WU73501A4 | B10: Guardian Angel Holding A Child And Flower (Mbz+Color) | C10: 20 | D10: 18 | E10: 27 | F10: 16.2 | G10: PC | H10: 4 | I10: WU | J10: =VLOOKUP(A10,'廣交會'!A:C,3,false) -> CF
A11: WU74800A4 | B11: Lion(Bronze) | C11: 34 | D11: 15 | E11: 26.5 | F11: 21 | G11: PC | H11: 1 | I11: WU | J11: =VLOOKUP(A11,'廣交會'!A:C,3,false) -> CF
A12: WU75168A4 | B12: Mozart | C12: 20.5 | D12: 14 | E12: 20 | F12: 22.2 | G12: PC | H12: 4 | I12: WU | J12: =VLOOKUP(A12,'廣交會'!A:C,3,false) -> CF
A13: WU75184AA | B13: King Cobra | C13: 32 | D13: 28.5 | E13: 33 | F13: 33 | G13: PC | H13: 1 | I13: WU | J13: =VLOOKUP(A13,'廣交會'!A:C,3,false) -> CF
A14: WU75218A4 | B14: St. Michael | C14: 16 | D14: 14 | E14: 28 | F14: 17.6 | G14: PC | H14: 6 | I14: WU | J14: =VLOOKUP(A14,'廣交會'!A:C,3,false) -> CF
A15: WU75321A4 | B15: Norse God - Freyr | C15: 20.5 | D15: 14.5 | E15: 28.5 | F15: 18.8 | G15: PC | H15: 4 | I15: WU | J15: =VLOOKUP(A15,'廣交會'!A:C,3,false) -> CF
A16: WU75357A4 | B16: Norse God – Odin | C16: 17 | D16: 12 | E16: 25 | F16: 17.5 | G16: PC | H16: 6 | I16: WU | J16: =VLOOKUP(A16,'廣交會'!A:C,3,false) -> CF
A17: WU75389AA | B17: Baby Zebra | C17: 15.7 | D17: 7.4 | E17: 17.5 | F17: 6.8 | G17: PC | H17: 24 | I17: WU | J17: =VLOOKUP(A17,'廣交會'!A:C,3,false) -> CF
A18: WU75452A4 | B18: Frederic Chopin | C18: 22 | D18: 16.5 | E18: 22 | F18: 23.5 | G18: PC | H18: 4 | I18: WU | J18: =VLOOKUP(A18,'廣交會'!A:C,3,false) -> CF
A19: WU75579AD | B19: Archangel Saint Michael Triumphs Over Evil | C19: 7.5 | D19: 3.5 | E19: 10.5 | F19: 3.2 | G19: PC | H19: 72 | I19: WU | J19: =VLOOKUP(A19,'廣交會'!A:C,3,false) -> CF
A20: WU75580AC | B20: Archangel Raphael Holding Spear And Shield | C20: 8.5 | D20: 4.5 | E20: 10 | F20: 3.2 | G20: PC | H20: 48 | I20: WU | J20: =VLOOKUP(A20,'廣交會'!A:C,3,false) -> CF
A21: WU75746AA | B21: White Wolf On Snowy Ground Looking Back | C21: 24 | D21: 15 | E21: 23.5 | F21: 12.6 | G21: PC | H21: 4 | I21: WU | J21: =VLOOKUP(A21,'廣交會'!A:C,3,false) -> CF
A22: WU75920A4 | B22: The Last Supper (Mbz+Color) | C22: 31.5 | D22: 6.5 | E22: 12 | F22: 19.2 | G22: PC | H22: 8 | J22: =VLOOKUP(A22,'廣交會'!A:C,3,false) -> CF
A23: WU75947A4 | B23: Zeus Fighting | C23: 16 | D23: 13 | E23: 28 | F23: 18.6 | G23: PC | H23: 6 | I23: TOPLAND | J23: =VLOOKUP(A23,'廣交會'!A:C,3,false) -> CF
A24: WU75978A4 | B24: St. Michael With Sword And A Balance (Mbz+Color) | C24: 16 | D24: 14 | E24: 28 | F24: 19.5 | G24: PC | H24: 6 | I24: WU | J24: =VLOOKUP(A24,'廣交會'!A:C,3,false) -> CF
A25: WU76006A4 | B25: Archangel - St. Gabriel (Mbz+Color) | C25: 19 | D25: 15.5 | E25: 33 | F25: 18.8 | G25: PC | H25: 4 | I25: WU | J25: =VLOOKUP(A25,'廣交會'!A:C,3,false) -> CF
A26: WU76038A4 | B26: Roman Warrior With Spear And Shield | C26: 16.5 | D26: 11.5 | E26: 35.5 | F26: 18 | G26: PC | H26: 6 | I26: WU | J26: =VLOOKUP(A26,'廣交會'!A:C,3,false) -> CF
A27: WU76067A4 | B27: Yemaya - Mother Of All And Goddess Of The Ocean | C27: 19 | D27: 9 | E27: 27 | F27: 14 | G27: PC | H27: 6 | I27: WU | J27: =VLOOKUP(A27,'廣交會'!A:C,3,false) -> CF
A28: WU76149AA | B28: Innocence | C28: 8 | D28: 7.5 | E28: 21.5 | F28: 8.8 | G28: PC | H28: 18 | I28: GOV | J28: =VLOOKUP(A28,'廣交會'!A:C,3,false) -> CF
A29: WU76165AA | B29: Panda Cub Walking | C29: 13 | D29: 6.5 | E29: 7.5 | F29: 4.8 | G29: PC | H29: 36 | J29: =VLOOKUP(A29,'廣交會'!A:C,3,false) -> CF
A30: WU76198AA | B30: Black Bear Cub Standing Up | C30: 7 | D30: 6.5 | E30: 14.5 | F30: 3.8 | G30: PC | H30: 48 | I30: WU | J30: =VLOOKUP(A30,'廣交會'!A:C,3,false) -> CF
A31: WU76207A4 | B31: Jazz Band -Female Singer | C31: 10 | D31: 10 | E31: 31 | F31: 16.5 | G31: PC | H31: 6 | I31: WU | J31: =VLOOKUP(A31,'廣交會'!A:C,3,false) -> CF
A32: WU76209A4 | B32: Medusa | C32: 13 | D32: 11 | E32: 22 | F32: 12.5 | G32: PC | H32: 12 | J32: =VLOOKUP(A32,'廣交會'!A:C,3,false) -> CF
A33: WU76218A5 | B33: Jazz Band -Saxophone Player | C33: 11 | D33: 12.5 | E33: 29 | F33: 16.8 | G33: PC | H33: 6 | I33: WU | J33: =VLOOKUP(A33,'廣交會'!A:C,3,false) -> CF
A34: WU76220A5 | B34: Jazz Band -Clarinet Player | C34: 14.5 | D34: 11 | E34: 31 | F34: 16.8 | G34: PC | H34: 6 | J34: =VLOOKUP(A34,'廣交會'!A:C,3,false) -> CF
A35: WU76221A5 | B35: Jazz Band -Guitar Player | C35: 12 | D35: 10 | E35: 32.5 | F35: 17 | G35: PC | H35: 6 | J35: =VLOOKUP(A35,'廣交會'!A:C,3,false) -> CF
A36: WU76231A4 | B36: Achilles With Spear & Shield | C36: 20 | D36: 11 | E36: 29 | F36: 18.8 | G36: PC | H36: 4 | I36: WU | J36: =VLOOKUP(A36,'廣交會'!A:C,3,false) -> CF
A37: WU76232A4 | B37: Hector With Sword & Shield | C37: 23 | D37: 18.5 | E37: 29.5 | F37: 17.8 | G37: PC | H37: 4 | I37: WU | J37: =VLOOKUP(A37,'廣交會'!A:C,3,false) -> CF
A38: WU76268AB | B38: Archangel- St. Gabriel With Trumpet | C38: 6 | D38: 4 | E38: 11 | F38: 3.2 | G38: PC | H38: 48 | I38: WU | J38: =VLOOKUP(A38,'廣交會'!A:C,3,false) -> CF
A39: WU76279A4 | B39: Poseidon On Hippocampus Chariot | C39: 26 | D39: 12.5 | E39: 19 | F39: 22.5 | G39: PC | H39: 4 | J39: =VLOOKUP(A39,'廣交會'!A:C,3,false) -> CF
A40: WU76289AA | B40: Archangel- Uriel | C40: 6 | D40: 4 | E40: 11.5 | F40: 3.2 | G40: PC | H40: 72 | I40: WU | J40: =VLOOKUP(A40,'廣交會'!A:C,3,false) -> CF
A41: WU76312A5 | B41: Archangel- St. Gabriel With Cross And Trumpet | C41: 16 | D41: 12.5 | E41: 23.5 | F41: 15 | G41: PC | H41: 6 | I41: GOV | J41: =VLOOKUP(A41,'廣交會'!A:C,3,false) -> CF
A42: WU76382AA | B42: Mary & Baby Jesus On The Donkey | C42: 17 | D42: 10.5 | E42: 22.5 | F42: 13.5 | G42: PC | H42: 6 | J42: =VLOOKUP(A42,'廣交會'!A:C,3,false) -> CF
A43: WU76403A4 | B43: Leonidas | C43: 26.5 | D43: 17 | E43: 34 | F43: 26.5 | G43: PC | H43: 2 | I43: WU | J43: =VLOOKUP(A43,'廣交會'!A:C,3,false) -> CF
A44: WU76423A4 | B44: Alexander The Great On Horseback | C44: 26.5 | D44: 11 | E44: 33.5 | F44: 26.8 | G44: PC | H44: 4 | I44: WU | J44: =VLOOKUP(A44,'廣交會'!A:C,3,false) -> CF
A45: WU76427A1 | B45: Merlin | C45: 12.5 | D45: 8.5 | E45: 30 | F45: 14.9 | G45: PC | H45: 12 | J45: =VLOOKUP(A45,'廣交會'!A:C,3,false) -> CF
A46: WU76459A4 | B46: Ludwig Van Beethoven - Bust | C46: 13 | D46: 10 | E46: 16.5 | F46: 9 | G46: PC | H46: 12 | J46: =VLOOKUP(A46,'廣交會'!A:C,3,false) -> CF
A47: WU76522A4 | B47: Elen Of The Ways - Antlered Goddess Of The Forest (Mbz+Color) | C47: 11 | D47: 9 | E47: 27.5 | F47: 14.5 | G47: PC | H47: 9 | I47: WU | J47: =VLOOKUP(A47,'廣交會'!A:C,3,false) -> CF
A48: WU76534A4 | B48: Leonidas With Spear And Shield | C48: 28.5 | D48: 24.5 | E48: 32.5 | F48: 22.5 | G48: PC | H48: 4 | I48: WU | J48: =VLOOKUP(A48,'廣交會'!A:C,3,false) -> CF
A49: WU76535A4 | B49: Steampunk Propeller Bookend (Mbz+Copper) | C49: 11.5 | D49: 9.5 | E49: 20.5 | F49: 12.5 | G49: PC | H49: 12 | J49: =VLOOKUP(A49,'廣交會'!A:C,3,false) -> CF
A50: WU76641A4 | B50: Hecate - Greek Goddess Of Magic | C50: 18 | D50: 14 | E50: 30 | F50: 21.2 | G50: PC | H50: 4 | I50: WU | J50: =VLOOKUP(A50,'廣交會'!A:C,3,false) -> CF
A51: WU76645A4 | B51: Little Dancer | C51: 18 | D51: 18 | E51: 42 | F51: 27 | G51: PC | H51: 2 | I51: WU | J51: =VLOOKUP(A51,'廣交會'!A:C,3,false) -> CF
A52: WU76649A4 | B52: Anubis Bust On Plinth | C52: 13 | D52: 12 | E52: 24 | F52: 15 | G52: PC | H52: 12 | J52: =VLOOKUP(A52,'廣交會'!A:C,3,false) -> CF
A53: WU76683V4 | B53: Steampunk Owl Clock | C53: 13 | D53: 13 | E53: 27 | F53: 21.2 | G53: PC | H53: 6 | I53: WU | J53: =VLOOKUP(A53,'廣交會'!A:C,3,false) -> CF
A54: WU76684A4 | B54: Celtic Pattern Treasure Chest Trinket Box (Green+Red) | C54: 15.7 | D54: 10.5 | E54: 10.5 | F54: 11.9 | G54: PC | H54: 18 | I54: WU | J54: =VLOOKUP(A54,'廣交會'!A:C,3,false) -> CF
A55: WU76737A4 | B55: Viking Warrior Whirling Axe | C55: 13.5 | D55: 9.5 | E55: 20 | F55: 11.2 | G55: PC | H55: 12 | I55: WU | J55: =VLOOKUP(A55,'廣交會'!A:C,3,false) -> CF
A56: WU76740AA | B56: Cosplay Kids - Pirate Girl With A Barrel Of Rum | C56: 7.5 | D56: 5.5 | E56: 15 | F56: 8 | G56: PC | H56: 36 | J56: =VLOOKUP(A56,'廣交會'!A:C,3,false) -> JH
A57: WU76755A4 | B57: Steampunk Octopus Trinket Box | C57: 10.5 | D57: 10.5 | E57: 9.5 | F57: 6.2 | G57: PC | H57: 24 | J57: =VLOOKUP(A57,'廣交會'!A:C,3,false) -> CF
A58: WU76782A4 | B58: Nandi - The Gatekeeper Of Shiva And Parvati | C58: 16 | D58: 8.5 | E58: 11 | F58: 10.5 | G58: PC | H58: 18 | J58: =VLOOKUP(A58,'廣交會'!A:C,3,false) -> CF
A59: WU76793A4 | B59: Oya - Goddess Of Wind, Storm And Transformation | C59: 13 | D59: 9 | E59: 24 | F59: 12.8 | G59: PC | H59: 8 | J59: =VLOOKUP(A59,'廣交會'!A:C,3,false) -> CF
A60: WU76808AA | B60: Call Of The Wild | C60: 16.5 | D60: 12 | E60: 13.5 | F60: 11.6 | G60: PC | H60: 12 | J60: =VLOOKUP(A60,'廣交會'!A:C,3,false) -> CF
A61: WU76826A4 | B61: Olokun - Owner Of The Deep Sea | C61: 17.5 | D61: 10 | E61: 36.5 | F61: 15.5 | G61: PC | H61: 6 | I61: WU | J61: =VLOOKUP(A61,'廣交會'!A:C,3,false) -> CF
A62: WU76837A4 | B62: Yemaya Standing On Ocean Wave | C62: 14 | D62: 12.5 | E62: 28.5 | F62: 15 | G62: PC | H62: 6 | J62: =VLOOKUP(A62,'廣交會'!A:C,3,false) -> CF
A63: WU76846A4 | B63: Steampunk Crow Skeleton | C63: 13.5 | D63: 6.5 | E63: 18 | F63: 9.2 | G63: PC | H63: 18 | J63: =VLOOKUP(A63,'廣交會'!A:C,3,false) -> CF
A64: WU76873A4 | B64: Norse God - Freya | C64: 12.5 | D64: 11.5 | E64: 26.5 | F64: 16 | G64: PC | H64: 8 | I64: WU | J64: =VLOOKUP(A64,'廣交會'!A:C,3,false) -> CF
A65: WU76908A4 | B65: Poseidon With Trident Standing On Hippocampus | C65: 20 | D65: 11 | E65: 21 | F65: 15.6 | G65: PC | H65: 6 | I65: 希臘/土耳其專賣 | J65: =VLOOKUP(A65,'廣交會'!A:C,3,false) -> CF
A66: WU76961A4 | B66: Gaia - Greek Primordial Goddess Of Earth | C66: 13.5 | D66: 11.5 | E66: 26 | F66: 16 | G66: PC | H66: 6 | I66: WU | J66: =VLOOKUP(A66,'廣交會'!A:C,3,false) -> CF
A67: WU76968A4 | B67: Gilgamesh - Legendary King Of Uruk | C67: 13 | D67: 10.5 | E67: 26.5 | F67: 16.5 | G67: PC | H67: 6 | J67: =VLOOKUP(A67,'廣交會'!A:C,3,false) -> CF
A68: WU76977AA | B68: Snow Owl Perching On Branch | C68: 15 | D68: 10 | E68: 17 | F68: 9.5 | G68: PC | H68: 12 | J68: =VLOOKUP(A68,'廣交會'!A:C,3,false) -> CF
A69: WU77001A4 | B69: Mermaid Lying Down 11 Inch | C69: 29 | D69: 11 | E69: 19.5 | F69: 13.5 | G69: PC | H69: 6 | I69: WU | J69: =VLOOKUP(A69,'廣交會'!A:C,3,false) -> CF
A70: WU77047A4 | B70: Octopus Mimic Chest Trinket Box | C70: 14.3 | D70: 9.8 | E70: 9.8 | F70: 11 | G70: PC | H70: 12 | I70: WU | J70: =VLOOKUP(A70,'廣交會'!A:C,3,false) -> CF
A71: WU77080A4 | B71: Saint Michael'S Prayer Photo Frame | C71: 14.5 | D71: 3 | E71: 19 | F71: 6.8 | G71: PC | H71: 16 | I71: wu | J71: =VLOOKUP(A71,'廣交會'!A:C,3,false) -> CF
A72: WU77083A5 | B72: Art Deco Style Female Figure Single Bookend (Cold Cast Copper) | C72: 15 | D72: 15.5 | E72: 23 | F72: 14.8 | G72: PC | H72: 6 | J72: =VLOOKUP(A72,'廣交會'!A:C,3,false) -> CF
A73: WU77085AA | B73: Celtic Triple Goddess Maiden Mother And The Crone | C73: 15 | D73: 14 | E73: 27 | F73: 19 | G73: PC | H73: 6 | I73: WU | J73: =VLOOKUP(A73,'廣交會'!A:C,3,false) -> CF
A74: WU77088A11 | B74: Armoured Dragon Night Light (Led) | C74: 13.5 | D74: 12 | E74: 24 | F74: 13.8 | G74: PC | H74: 6 | I74: WU | J74: =VLOOKUP(A74,'廣交會'!A:C,3,false) -> CF
A75: WU77090A4 | B75: Brigid - Goddess Of Hearth And Home | C75: 18 | D75: 14 | E75: 24.5 | F75: 18.4 | G75: PC | H75: 6 | J75: =VLOOKUP(A75,'廣交會'!A:C,3,false) -> CF
A76: WU77107AA | B76: Charon - Ferryman Of The Greek Underworld (Led Lantern) | C76: 27 | D76: 11.5 | E76: 25 | F76: 17.8 | G76: PC | H76: 6 | J76: =VLOOKUP(A76,'廣交會'!A:C,3,false) -> CF
A77: WU77116A4 | B77: Centaur Shooting Bow | C77: 28 | D77: 10.5 | E77: 37 | F77: 21 | G77: PC | H77: 1 | I77: WU | J77: =VLOOKUP(A77,'廣交會'!A:C,3,false) -> CF
A78: WU77126A4 | B78: Flight Of Icarus | C78: 25.5 | D78: 10 | E78: 37 | F78: 16.8 | G78: PC | H78: 3 | J78: =VLOOKUP(A78,'廣交會'!A:C,3,false) -> CF
A79: WU77171AA | B79: Dechainee By Melanie Delon | C79: 20.5 | D79: 14 | E79: 20.5 | F79: 16.6 | G79: PC | H79: 8 | I79: WU | J79: =VLOOKUP(A79,'廣交會'!A:C,3,false) -> CF
A80: WU77221A4 | B80: Tyr And The Binding Of Fenrir | C80: 24.5 | D80: 18 | E80: 22.5 | F80: 23.2 | G80: PC | H80: 4 | I80: WU | J80: =VLOOKUP(A80,'廣交會'!A:C,3,false) -> CF
A81: WU77252A4 | B81: Ceridwen - Celtic Goddess Of Fertility And Inspiration | C81: 17 | D81: 17 | E81: 16 | F81: 15.6 | G81: PC | H81: 8 | I81: WU | J81: =VLOOKUP(A81,'廣交會'!A:C,3,false) -> CF
A82: WU77274AA | B82: Horned Obsidian Dragon Bust (Led) | C82: 16 | D82: 12 | E82: 20.5 | F82: 16.5 | G82: PC | H82: 8 | I82: WU | J82: =VLOOKUP(A82,'廣交會'!A:C,3,false) -> CF
A83: WU77288VA | B83: Horned Azure Dragon Bust | C83: 16 | D83: 12.5 | E83: 20.5 | F83: 12.9 | G83: PC | H83: 8 | I83: WU | J83: =VLOOKUP(A83,'廣交會'!A:C,3,false) -> CF
A84: WU77291A4 | B84: Constantine Xi Palaiologos Holding Flag Of Byzantine Empire | C84: 17.5 | D84: 9.5 | E84: 32 | F84: 16.5 | G84: PC | H84: 6 | I84: IB.GR | J84: =VLOOKUP(A84,'廣交會'!A:C,3,false) -> CF
A85: WU77309A4 | B85: Athena | C85: 8.2 | D85: 7 | E85: 20.5 | F85: 10.5 | G85: PC | H85: 18 | I85: WU | J85: =VLOOKUP(A85,'廣交會'!A:C,3,false) -> CF
A86: WU77313A4 | B86: Triremes Greek Warship | C86: 35 | D86: 22 | E86: 26.5 | F86: 32.8 | G86: PC | H86: 1 | J86: =VLOOKUP(A86,'廣交會'!A:C,3,false) -> CF
A87: WU77318A4 | B87: Acorn Tree Ent Round Trinket Box | C87: 9.5 | D87: 9.5 | E87: 6 | F87: 6.8 | G87: PC | H87: 36 | J87: =VLOOKUP(A87,'廣交會'!A:C,3,false) -> CF
A88: WU77326AC | B88: Thorny Scale Dragon Eye Trinket Box | C88: 13 | D88: 10 | E88: 8.6 | F88: 9.3 | G88: PC | H88: 24 | J88: =VLOOKUP(A88,'廣交會'!A:C,3,false) -> CF
A89: WU77328AA | B89: Faery Of Ravens By Nene Thomas | C89: 19 | D89: 12.5 | E89: 31.5 | F89: 26.2 | G89: PC | H89: 4 | I89: WU | J89: =VLOOKUP(A89,'廣交會'!A:C,3,false) -> PL
A90: WU77329A4 | B90: The Druid By Ruth Thompson | C90: 13 | D90: 7 | E90: 27 | F90: 22.6 | G90: PC | H90: 8 | I90: WU | J90: =VLOOKUP(A90,'廣交會'!A:C,3,false) -> CF
A91: WU77369AA | B91: Guidance By Lisa Parker | C91: 21 | D91: 20 | E91: 25 | F91: 24.2 | G91: PC | H91: 4 | I91: NEM | J91: =VLOOKUP(A91,'廣交會'!A:C,3,false) -> CF
A92: WU77379A4 | B92: Galileo Galilei Seeing Through The Looking Glass | C92: 15.2 | D92: 13.3 | E92: 21 | F92: 18.5 | G92: PC | H92: 8 | J92: =VLOOKUP(A92,'廣交會'!A:C,3,false) -> CF
A93: WU77380A4 | B93: Three Kings - Melchior (Three Magi) | C93: 11.5 | D93: 4.8 | E93: 13.5 | F93: 6.3 | G93: PC | H93: 36 | J93: =VLOOKUP(A93,'廣交會'!A:C,3,false) -> CF
A94: WU77381A4 | B94: Three Kings - Caspar (Three Magi) | C94: 10.5 | D94: 4.3 | E94: 12.5 | F94: 6.5 | G94: PC | H94: 36 | J94: =VLOOKUP(A94,'廣交會'!A:C,3,false) -> CF
A95: WU77382A4 | B95: Three Kings - Balthazar(Three Magi) | C95: 11.5 | D95: 5 | E95: 13.2 | F95: 6.5 | G95: PC | H95: 36 | J95: =VLOOKUP(A95,'廣交會'!A:C,3,false) -> CF
A96: WU77383A4 | B96: Hephaestus - Greek God Of Fire, Masonry And The Forge | C96: 11.2 | D96: 11.6 | E96: 22 | F96: 12 | G96: PC | H96: 12 | I96: WU | J96: =VLOOKUP(A96,'廣交會'!A:C,3,false) -> CF
A97: WU77385A4 | B97: Ludwig Van Beethoven Sitting Music Box (Symphony No.5) | C97: 13.6 | D97: 16.5 | E97: 26.5 | F97: 17.2 | G97: PC | H97: 6 | I97: WU | J97: =VLOOKUP(A97,'廣交會'!A:C,3,false) -> CF
A98: WU77386A4 | B98: Celtic Dragon Crest Round Trinket Box | C98: 9.5 | D98: 9.5 | E98: 5.7 | F98: 5.2 | G98: PC | H98: 36 | I98: WU | J98: =VLOOKUP(A98,'廣交會'!A:C,3,false) -> CF
A99: WU77389A4 | B99: Steampunk Tortoise Trinket Box | C99: 18.5 | D99: 11.5 | E99: 10.5 | F99: 11.5 | G99: PC | H99: 12 | J99: =VLOOKUP(A99,'廣交會'!A:C,3,false) -> CF
A100: WU77399A4 | B100: Athena Standing Under Sacred Olive Tree | C100: 14 | D100: 9.3 | E100: 24.5 | F100: 14.8 | G100: PC | H100: 8 | J100: =VLOOKUP(A100,'廣交會'!A:C,3,false) -> CF
...
